Workbook

Sheet Framework
A1: VIACONNECT • HEALTH CHECK — Maturidade dos Domínios do SOC (versão completa)
A2: Sistema de avaliação · um domínio por aba · estrutura e nomenclatura fiéis ao framework oficial de cada domínio
A4: 1. Sobre este instrumento
A5: Esta versão reproduz fielmente a estrutura de cada framework de referência: os parâmetros do SIM3 (O/H/T/P, 45 itens), os 11 domínios do CTI-CMM alinhados ao C2M2, os 15 passos do CREST em 3 fases, as 6 áreas de serviço do FIRST PSIRT, os 5 domínios PIACT do SANS VMMM, os 3 pilares da Detection Engineering Maturity Matrix, as 5 colunas do MITRE Engage e o ciclo PEAK/HMM de threat hunting. Cada item usa a nomenclatura oficial (ex.: O-1 Mandate, P-8 Audit & Feedback).
A6: Como cada framework usa uma escala própria (CTI0–CTI3, HMM0–HMM4, 0–4 do SIM3, 0–3 do PSIRT, 1–5 do CREST/VMMM), a aba Dash normaliza tudo em percentual de maturidade (nível ÷ máximo da escala) para permitir o radar comparativo entre os 9 domínios. Os itens são autorais: descrevem o que avaliar, sem reproduzir texto proprietário dos manuais originais.
A8: 2. Modelos de referência usados neste arquivo
A9: Aba | B9: Modelo de referência | C9: Mantenedor | D9: Escala | E9: Referência oficial
A10: CTI | B10: CTI-CMM v2 — 11 domínios alinhados ao C2M2 | C10: Comunidade CTI-CMM | D10: 0–3 (CTI0–CTI3) | E10: https://cti-cmm.org
A11: Threat Hunting | B11: PEAK (Prepare/Execute/Act) + HMM | C11: D. Bianco, R. Fetterman / Splunk | D11: 0–4 (HMM0–HMM4) | E11: https://www.splunk.com · https://www.threathunting.net
A12: Detection Eng | B12: Detection Engineering Maturity Matrix (3 pilares) | C12: Kyle Bailey | D12: 1–5 | E12: https://detectionengineering.io
A13: DFIR | B13: CREST CSIR Maturity Assessment — 15 passos / 3 fases | C13: CREST | D13: 1–5 | E13: https://www.crest-approved.org
A14: CSIRT | B14: SIM3 v2 interim — 45 parâmetros (O/H/T/P) | C14: Open CSIRT Foundation | D14: 0–4 | E14: https://opencsirt.org/csirt-maturity/sim3-and-references/
A15: PSIRT | B15: FIRST PSIRT Services Framework — 6 áreas de serviço | C15: FIRST.org | D15: 0–3 | E15: https://www.first.org/standards/frameworks/psirts/
A16: Deception | B16: MITRE Engage — Prepare/Expose/Affect/Elicit/Understand | C16: MITRE | D16: 0–5 (adaptada) | E16: https://engage.mitre.org
A17: Vuln Mgmt | B17: SANS VMMM — ciclo PIACT (5 domínios) | C17: SANS · J. Risto / D. Hazar | D17: 1–5 | E17: https://www.sans.org/blog/vulnerability-management-maturity-model
A18: Automacao | B18: SOC-CMM (Automation & Orchestration) + INFORM | C18: soc-cmm.com / MITRE CTID | D18: 0–5 (adaptada) | E18: https://www.soc-cmm.com · https://ctid.mitre.org
A20: 3. Escalas de maturidade
A21: Escala CTI-CMM (CTI0–CTI3)
A22: 0 | B22: CTI0 · Pré-fundacional | C22: Nenhuma atividade de inteligência de ameaças realizada nesta área.
A23: 1 | B23: CTI1 · Fundacional | C23: Atividades ad hoc, não planejadas e reativas.
A24: 2 | B24: CTI2 · Avançado | C24: Atividades planejadas, consistentes e repetíveis, com foco em resultados de curto e médio prazo.
A25: 3 | B25: CTI3 · Líder | C25: Práticas mensuráveis e alinhadas a resultados de negócio, com recomendações de longo prazo.
A27: Escala HMM — Hunting Maturity Model (HMM0–HMM4)
A28: 0 | B28: HMM0 · Inicial | C28: Dependência exclusiva de alertas automáticos; pouca coleta de dados; sem capacidade de hunting.
A29: 1 | B29: HMM1 · Mínimo | C29: Incorpora inteligência de ameaças e faz buscas pontuais sobre coleta moderada de dados.
A30: 2 | B30: HMM2 · Procedural | C30: Executa regularmente procedimentos de hunting criados por terceiros, com boa coleta de dados.
A31: 3 | B31: HMM3 · Inovador | C31: Cria e documenta procedimentos próprios de hunting com técnicas analíticas variadas.
A32: 4 | B32: HMM4 · Líder | C32: Automatiza os procedimentos bem-sucedidos e concentra o esforço humano em inovação contínua.
A34: Escala 1–5 (estilo CMMI, usada por CREST, SANS VMMM, RTCMM e PTMM)
A35: 1 | B35: Inicial | C35: Prática ad hoc e imprevisível; depende de esforço individual.
A36: 2 | B36: Gerenciado | C36: Repetível e gerenciada caso a caso, com disciplina básica.
A37: 3 | B37: Definido | C37: Padronizada e documentada para toda a organização.
A38: 4 | B38: Medido quantitativamente | C38: Controlada com métricas e metas de desempenho.
A39: 5 | B39: Otimizado | C39: Foco em melhoria contínua e otimização baseada em dados.
A41: Escala SIM3 (0–4)
A42: 0 | B42: Indisponível / indefinido | C42: O parâmetro não existe ou não está definido para o time.
A43: 1 | B43: Implícito | C43: Conhecido e praticado de forma tácita ("sempre fizemos assim"), sem registro escrito.
A44: 2 | B44: Explícito, interno | C44: Documentado e disponível dentro do time, sem formalização superior.
A45: 3 | B45: Explícito, formalizado | C45: Documentado e aprovado formalmente pela liderança responsável pelo time.
A46: 4 | B46: Explícito, auditado | C46: Formalizado e sujeito a controle/auditoria por níveis de governança acima do time.
A48: Escala PSIRT (0–3, conforme níveis do PSIRT Maturity Document)
A49: 0 | B49: Inexistente | C49: Não há capacidade estabelecida para o item.
A50: 1 | B50: Básico | C50: Capacidades essenciais montadas; operação predominantemente reativa.
A51: 2 | B51: Intermediário | C51: Políticas e processos formalizados; transição do reativo para o proativo.
A52: 3 | B52: Avançado | C52: Processos refinados, integrados ao ciclo de desenvolvimento e operando proativamente.
A54: Escala 0–5 (estilo SOC-CMM / CMMI)
A55: 0 | B55: Inexistente | C55: A prática não existe ou não há qualquer evidência dela.
A56: 1 | B56: Inicial (ad hoc) | C56: Executada de forma pontual, dependente de pessoas específicas, sem documentação.
A57: 2 | B57: Repetível | C57: Executada de forma consistente, com documentação parcial e resultados ainda variáveis.
A58: 3 | B58: Definido | C58: Documentada, padronizada, comunicada e efetivamente seguida pela equipe.
A59: 4 | B59: Gerenciado e medido | C59: Acompanhada por indicadores; decisões de melhoria baseadas em dados.
A60: 5 | B60: Otimizado | C60: Em melhoria contínua estruturada, integrada aos demais processos.
A62: 4. Como usar
A63: 1. Em cada aba, selecione em "Avaliação atual" o nível observado usando a escala oficial daquele framework (seção 3).
A64: 2. Defina em "Meta" o nível-alvo. No CREST e no SIM3, o alvo costuma variar por criticidade do ativo/serviço.
A65: 3. Registre evidências (documentos, telas, entrevistas) que sustentem cada nota — exigência de níveis altos no SIM3/CREST.
A66: 4. Abra a aba Dash: maturidade geral, radar dos 9 domínios, barras por categoria e um gráfico próprio por domínio com seus subdomínios.
A67: 5. Lembre: maturidade máxima nem sempre é o objetivo. Calibre a meta de cada domínio à necessidade real do cliente.
A68: 6. Reavalie periodicamente para evidenciar a evolução ao longo do tempo.
A70: Instrumento autoral Viaconnect que segue a ESTRUTURA e a NOMENCLATURA pública de cada framework, sem reproduzir o texto proprietário dos manuais. Para avaliação oficial/certificável use a ferramenta original do mantenedor (SIM3 self-assessment da OCF, CREST CSIR tool, planilha CTI-CMM, etc.). SIM3 © Open CSIRT Foundation; CREST © CREST; PSIRT Services Framework © FIRST; MITRE Engage © The MITRE Corporation; PEAK/HMM © Splunk/D. Bianco; VMMM © SANS.

Sheet CTI
A1: CTI — Cyber Threat Intelligence (CTI-CMM v2)
A2: CTI-CMM v2 · 11 domínios alinhados ao C2M2, cada um com a "CTI Mission" que o sustenta · escala CTI0–CTI3 (stakeholder-first).
A3: Como preencher: selecione o nível observado em "Avaliação atual" e o nível desejado em "Meta". As colunas Nível, Nível meta e Gap calculam automaticamente. Registre em "Evidências" o que sustenta a nota.
A4: ID | B4: Item de avaliação | C4: Orientação para o avaliador | D4: Avaliação atual | E4: Nível | F4: Meta (nível desejado) | G4: Nível meta | H4: Gap | I4: Evidências / observações | K4: MATURIDADE POR SUBDOMÍNIO
A5: PROGRAM · Gestão do Programa de CTI | K5: Subdomínio | L5: Atual | M5: Meta
A6: CTI-01 | B6: A CTI possui requisitos prioritários de inteligência (PIRs) definidos com os stakeholders e revisados. | C6: Domínio Program Management do C2M2. O CTI-CMM é stakeholder-first: sem PIRs a coleta não tem direção. | E6: =IF($D6="","",VALUE(LEFT($D6,1))) | G6: =IF($F6="","",VALUE(LEFT($F6,1))) | H6: =IF(OR($E6="",$G6=""),"",$G6-$E6) | K6: PROGRAM | L6: =IFERROR(AVERAGE($E$6:$E$8)/3,0) -> 0 | M6: =IFERROR(AVERAGE($G$6:$G$8)/3,0) -> 0
A7: CTI-02 | B7: Papéis, governança e orçamento da função de CTI estão estabelecidos. | C7: Avalie mandato, reporte e sustentação financeira da função. | E7: =IF($D7="","",VALUE(LEFT($D7,1))) | G7: =IF($F7="","",VALUE(LEFT($F7,1))) | H7: =IF(OR($E7="",$G7=""),"",$G7-$E7) | K7: ASSET | L7: =IFERROR(AVERAGE($E$10:$E$11)/3,0) -> 0 | M7: =IFERROR(AVERAGE($G$10:$G$11)/3,0) -> 0
A8: CTI-03 | B8: O valor da CTI é medido e comunicado às lideranças (métricas de impacto por stakeholder). | C8: CTI3 exige práticas mensuráveis ligadas a resultado de negócio. | E8: =IF($D8="","",VALUE(LEFT($D8,1))) | G8: =IF($F8="","",VALUE(LEFT($F8,1))) | H8: =IF(OR($E8="",$G8=""),"",$G8-$E8) | K8: THREAT | L8: =IFERROR(AVERAGE($E$13:$E$15)/3,0) -> 0 | M8: =IFERROR(AVERAGE($G$13:$G$15)/3,0) -> 0
A9: ASSET · Asset, Change & Configuration Management | K9: RISK | L9: =IFERROR(AVERAGE($E$17:$E$18)/3,0) -> 0 | M9: =IFERROR(AVERAGE($G$17:$G$18)/3,0) -> 0
A10: CTI-04 | B10: A CTI apoia a gestão de superfície de ataque e de ativos expostos (EASM, shadow IT). | C10: CTI Mission do domínio Asset: reduzir exposição informando o inventário e a superfície. | E10: =IF($D10="","",VALUE(LEFT($D10,1))) | G10: =IF($F10="","",VALUE(LEFT($F10,1))) | H10: =IF(OR($E10="",$G10=""),"",$G10-$E10) | K10: SITUATION | L10: =IFERROR(AVERAGE($E$20:$E$21)/3,0) -> 0 | M10: =IFERROR(AVERAGE($G$20:$G$21)/3,0) -> 0
A11: CTI-05 | B11: Inteligência sobre exposições alimenta priorização de mudanças e configurações. | C11: Avalie se achados de exposição externa chegam aos donos de ativos. | E11: =IF($D11="","",VALUE(LEFT($D11,1))) | G11: =IF($F11="","",VALUE(LEFT($F11,1))) | H11: =IF(OR($E11="",$G11=""),"",$G11-$E11) | K11: RESPONSE | L11: =IFERROR(AVERAGE($E$23:$E$24)/3,0) -> 0 | M11: =IFERROR(AVERAGE($G$23:$G$24)/3,0) -> 0
A12: THREAT · Threat & Vulnerability Management | K12: ACCESS | L12: =IFERROR(AVERAGE($E$26:$E$27)/3,0) -> 0 | M12: =IFERROR(AVERAGE($G$26:$G$27)/3,0) -> 0
A13: CTI-06 | B13: A CTI apoia a priorização de vulnerabilidades com contexto de exploração ativa e ator. | C13: Domínio fundamental (THREAT). Procure inteligência alimentando patch prioritization (KEV/EPSS + ator). | E13: =IF($D13="","",VALUE(LEFT($D13,1))) | G13: =IF($F13="","",VALUE(LEFT($F13,1))) | H13: =IF(OR($E13="",$G13=""),"",$G13-$E13) | K13: WORKFORCE | L13: =IFERROR(AVERAGE($E$29:$E$30)/3,0) -> 0 | M13: =IFERROR(AVERAGE($G$29:$G$30)/3,0) -> 0
A14: CTI-07 | B14: A CTI apoia detection engineering e o SOC com TTPs e IOCs contextualizados. | C14: O THREAT sustenta vuln mgmt, detecção e SOC — missão central do CTI segundo o modelo. | E14: =IF($D14="","",VALUE(LEFT($D14,1))) | G14: =IF($F14="","",VALUE(LEFT($F14,1))) | H14: =IF(OR($E14="",$G14=""),"",$G14-$E14) | K14: ARCHITECTURE | L14: =IFERROR(AVERAGE($E$32:$E$33)/3,0) -> 0 | M14: =IFERROR(AVERAGE($G$32:$G$33)/3,0) -> 0
A15: CTI-08 | B15: A CTI mantém perfis de atores relevantes ao setor e à geografia do cliente. | C15: Avalie cobertura de adversários priorizados e mapeamento a ATT&CK. | E15: =IF($D15="","",VALUE(LEFT($D15,1))) | G15: =IF($F15="","",VALUE(LEFT($F15,1))) | H15: =IF(OR($E15="",$G15=""),"",$G15-$E15) | K15: THIRD-PARTIES | L15: =IFERROR(AVERAGE($E$35:$E$36)/3,0) -> 0 | M15: =IFERROR(AVERAGE($G$35:$G$36)/3,0) -> 0
A16: RISK · Risk Management | K16: FRAUD | L16: =IFERROR(AVERAGE($E$38:$E$39)/3,0) -> 0 | M16: =IFERROR(AVERAGE($G$38:$G$39)/3,0) -> 0
A17: CTI-09 | B17: A CTI fornece avaliações de risco informadas por ameaça (threat-informed risk). | C17: CTI Mission do domínio Risk: quantificar risco com base no cenário de ameaças real. | E17: =IF($D17="","",VALUE(LEFT($D17,1))) | G17: =IF($F17="","",VALUE(LEFT($F17,1))) | H17: =IF(OR($E17="",$G17=""),"",$G17-$E17)
A18: CTI-10 | B18: A inteligência apoia decisões de aceitação e tratamento de risco. | C18: Procure exemplos de decisões de risco influenciadas por produtos de CTI. | E18: =IF($D18="","",VALUE(LEFT($D18,1))) | G18: =IF($F18="","",VALUE(LEFT($F18,1))) | H18: =IF(OR($E18="",$G18=""),"",$G18-$E18)
A19: SITUATION · Situational Awareness
A20: CTI-11 | B20: A CTI estabelece consciência situacional do cenário de ameaças (atual e prospectivo). | C20: Domínio Situation: coletar, monitorar, analisar, alarmar e reportar para reduzir incerteza. | E20: =IF($D20="","",VALUE(LEFT($D20,1))) | G20: =IF($F20="","",VALUE(LEFT($F20,1))) | H20: =IF(OR($E20="",$G20=""),"",$G20-$E20)
A21: CTI-12 | B21: Produtos estratégicos, operacionais e táticos são entregues aos públicos certos. | C21: Cada público consome um nível diferente; avalie exemplos reais dos três. | E21: =IF($D21="","",VALUE(LEFT($D21,1))) | G21: =IF($F21="","",VALUE(LEFT($F21,1))) | H21: =IF(OR($E21="",$G21=""),"",$G21-$E21)
A22: RESPONSE · Event & Incident Response, Continuity
A23: CTI-13 | B23: A CTI apoia a resposta a incidentes com enriquecimento de indicadores e atribuição. | C23: Domínio RESPONSE: missão fundamental do CTI junto ao IR. Procure CTI dentro do ciclo de resposta. | E23: =IF($D23="","",VALUE(LEFT($D23,1))) | G23: =IF($F23="","",VALUE(LEFT($F23,1))) | H23: =IF(OR($E23="",$G23=""),"",$G23-$E23)
A24: CTI-14 | B24: Lições de incidentes retroalimentam requisitos e produção de inteligência. | C24: Feche o ciclo: o incidente deve gerar novos PIRs e detecções. | E24: =IF($D24="","",VALUE(LEFT($D24,1))) | G24: =IF($F24="","",VALUE(LEFT($F24,1))) | H24: =IF(OR($E24="",$G24=""),"",$G24-$E24)
A25: ACCESS · Identity & Access Management
A26: CTI-15 | B26: A CTI informa estratégias de identidade com inteligência sobre ameaças a credenciais e acesso. | C26: CTI Mission do domínio Access: passar de "gerir logins" para "gerir risco de identidade". | E26: =IF($D26="","",VALUE(LEFT($D26,1))) | G26: =IF($F26="","",VALUE(LEFT($F26,1))) | H26: =IF(OR($E26="",$G26=""),"",$G26-$E26)
A27: CTI-16 | B27: Inteligência sobre vazamento de credenciais e abuso de identidade é monitorada e acionável. | C27: Avalie monitoramento de credential leaks e resposta associada. | E27: =IF($D27="","",VALUE(LEFT($D27,1))) | G27: =IF($F27="","",VALUE(LEFT($F27,1))) | H27: =IF(OR($E27="",$G27=""),"",$G27-$E27)
A28: WORKFORCE · Workforce Management
A29: CTI-17 | B29: A CTI provê capacitação e conscientização baseada em ameaças reais ao cliente. | C29: CTI Mission do domínio Workforce: treinar com base no que ameaça de fato a organização. | E29: =IF($D29="","",VALUE(LEFT($D29,1))) | G29: =IF($F29="","",VALUE(LEFT($F29,1))) | H29: =IF(OR($E29="",$G29=""),"",$G29-$E29)
A30: CTI-18 | B30: A competência da equipe de CTI é desenvolvida (OSINT, análise, ferramentas). | C30: Treinamento contínuo sustenta a evolução do programa. | E30: =IF($D30="","",VALUE(LEFT($D30,1))) | G30: =IF($F30="","",VALUE(LEFT($F30,1))) | H30: =IF(OR($E30="",$G30=""),"",$G30-$E30)
A31: ARCHITECTURE · Cybersecurity Architecture
A32: CTI-19 | B32: A CTI informa decisões de arquitetura de segurança com base em ameaças e TTPs. | C32: CTI Mission do domínio Architecture: orientar controles pelo comportamento adversário. | E32: =IF($D32="","",VALUE(LEFT($D32,1))) | G32: =IF($F32="","",VALUE(LEFT($F32,1))) | H32: =IF(OR($E32="",$G32=""),"",$G32-$E32)
A33: CTI-20 | B33: Inteligência apoia priorização de controles defensivos e defense-in-depth. | C33: Avalie se a arquitetura é guiada por ameaça e não só por compliance. | E33: =IF($D33="","",VALUE(LEFT($D33,1))) | G33: =IF($F33="","",VALUE(LEFT($F33,1))) | H33: =IF(OR($E33="",$G33=""),"",$G33-$E33)
A34: THIRD-PARTIES · Third-Party Risk Management
A35: CTI-21 | B35: A CTI fornece inteligência sobre risco de terceiros e cadeia de suprimentos. | C35: CTI Mission do domínio Third-Parties: monitorar exposição de fornecedores e supply chain. | E35: =IF($D35="","",VALUE(LEFT($D35,1))) | G35: =IF($F35="","",VALUE(LEFT($F35,1))) | H35: =IF(OR($E35="",$G35=""),"",$G35-$E35)
A36: CTI-22 | B36: Comprometimentos de terceiros relevantes são monitorados e comunicados. | C36: Avalie monitoramento de breaches em fornecedores críticos. | E36: =IF($D36="","",VALUE(LEFT($D36,1))) | G36: =IF($F36="","",VALUE(LEFT($F36,1))) | H36: =IF(OR($E36="",$G36=""),"",$G36-$E36)
A37: FRAUD · Fraud (apêndice CTI-CMM v1.1+)
A38: CTI-23 | B38: A CTI apoia a prevenção e detecção de fraude com inteligência específica. | C38: Domínio Fraud adicionado na v1.1. Aplique conforme o cliente tenha exposição a fraude. | E38: =IF($D38="","",VALUE(LEFT($D38,1))) | G38: =IF($F38="","",VALUE(LEFT($F38,1))) | H38: =IF(OR($E38="",$G38=""),"",$G38-$E38)
A39: CTI-24 | B39: Tendências de fraude e kits/serviços do submundo são monitorados. | C39: Avalie monitoramento de dark web e fraud intelligence quando aplicável. | E39: =IF($D39="","",VALUE(LEFT($D39,1))) | G39: =IF($F39="","",VALUE(LEFT($F39,1))) | H39: =IF(OR($E39="",$G39=""),"",$G39-$E39)

Sheet Threat Hunting
A1: THREAT HUNTING — PEAK (Prepare · Execute · Act) + HMM
A2: Framework PEAK (Splunk/Bianco-Fetterman) estruturado em Prepare/Execute/Act, três tipos de hunt e a hierarquia de saídas; maturidade pelo HMM0–HMM4.
A3: Como preencher: selecione o nível observado em "Avaliação atual" e o nível desejado em "Meta". As colunas Nível, Nível meta e Gap calculam automaticamente. Registre em "Evidências" o que sustenta a nota.
A4: ID | B4: Item de avaliação | C4: Orientação para o avaliador | D4: Avaliação atual | E4: Nível | F4: Meta (nível desejado) | G4: Nível meta | H4: Gap | I4: Evidências / observações | K4: MATURIDADE POR SUBDOMÍNIO
A5: PREPARE · Preparação do hunt | K5: Subdomínio | L5: Atual | M5: Meta
A6: TH-01 | B6: As hipóteses são formuladas com o teste ABLE (Actor, Behavior, Location, Evidence). | C6: PEAK recomenda o ABLE para garantir que a hipótese seja testável com os dados disponíveis. | E6: =IF($D6="","",VALUE(LEFT($D6,1))) | G6: =IF($F6="","",VALUE(LEFT($F6,1))) | H6: =IF(OR($E6="",$G6=""),"",$G6-$E6) | K6: PREPARE | L6: =IFERROR(AVERAGE($E$6:$E$9)/4,0) -> 0 | M6: =IFERROR(AVERAGE($G$6:$G$9)/4,0) -> 0
A7: TH-02 | B7: O escopo e o plano do hunt são definidos antes da execução (dados, janela, ativos-alvo). | C7: Fase Prepare do PEAK: escopo claro evita hunts errantes e improdutivos. | E7: =IF($D7="","",VALUE(LEFT($D7,1))) | G7: =IF($F7="","",VALUE(LEFT($F7,1))) | H7: =IF(OR($E7="",$G7=""),"",$G7-$E7) | K7: EXECUTE | L7: =IFERROR(AVERAGE($E$11:$E$14)/4,0) -> 0 | M7: =IFERROR(AVERAGE($G$11:$G$14)/4,0) -> 0
A8: TH-03 | B8: A telemetria necessária (endpoint, rede, identidade, nuvem) está disponível e pesquisável. | C8: No HMM, a abrangência e o acesso aos dados determinam fortemente o nível de maturidade. | E8: =IF($D8="","",VALUE(LEFT($D8,1))) | G8: =IF($F8="","",VALUE(LEFT($F8,1))) | H8: =IF(OR($E8="",$G8=""),"",$G8-$E8) | K8: ACT · Documentação, | L8: =IFERROR(AVERAGE($E$16:$E$19)/4,0) -> 0 | M8: =IFERROR(AVERAGE($G$16:$G$19)/4,0) -> 0
A9: TH-04 | B9: A retenção permite investigar a janela temporal relevante da hipótese. | C9: Campanhas se estendem por semanas/meses; avalie a janela efetivamente pesquisável. | E9: =IF($D9="","",VALUE(LEFT($D9,1))) | G9: =IF($F9="","",VALUE(LEFT($F9,1))) | H9: =IF(OR($E9="",$G9=""),"",$G9-$E9) | K9: MÉTRICAS | L9: =IFERROR(AVERAGE($E$21:$E$22)/4,0) -> 0 | M9: =IFERROR(AVERAGE($G$21:$G$22)/4,0) -> 0
A10: EXECUTE · Execução do hunt
A11: TH-05 | B11: Hunts hypothesis-driven (baseados em hipótese) são executados regularmente. | C11: Primeiro tipo de hunt do PEAK. Cadência regular distingue programa de iniciativa pontual. | E11: =IF($D11="","",VALUE(LEFT($D11,1))) | G11: =IF($F11="","",VALUE(LEFT($F11,1))) | H11: =IF(OR($E11="",$G11=""),"",$G11-$E11)
A12: TH-06 | B12: Hunts baseline (data-driven) estabelecem o normal para revelar desvios. | C12: Segundo tipo do PEAK: caracterizar o ambiente para expor anomalias. | E12: =IF($D12="","",VALUE(LEFT($D12,1))) | G12: =IF($F12="","",VALUE(LEFT($F12,1))) | H12: =IF(OR($E12="",$G12=""),"",$G12-$E12)
A13: TH-07 | B13: Hunts model-assisted (M-ATH) usam modelos/ML para escalar a análise. | C13: Terceiro tipo do PEAK. Programas maduros evoluem para apoio algorítmico (HMM3–HMM4). | E13: =IF($D13="","",VALUE(LEFT($D13,1))) | G13: =IF($F13="","",VALUE(LEFT($F13,1))) | H13: =IF(OR($E13="",$G13=""),"",$G13-$E13)
A14: TH-08 | B14: A análise dos hunters cobre além de IOCs, focando comportamentos e TTPs (Pyramid of Pain). | C14: Habilidade analítica é um dos três eixos do HMM; subir na pirâmide aumenta o valor do hunt. | E14: =IF($D14="","",VALUE(LEFT($D14,1))) | G14: =IF($F14="","",VALUE(LEFT($F14,1))) | H14: =IF(OR($E14="",$G14=""),"",$G14-$E14)
A15: ACT · Documentação, automação e comunicação
A16: TH-09 | B16: Cada hunt é documentado em formato padronizado (escopo, dados, achados, lições). | C16: Fase Act do PEAK. Documentação permite repetir, auditar e transferir conhecimento. | E16: =IF($D16="","",VALUE(LEFT($D16,1))) | G16: =IF($F16="","",VALUE(LEFT($F16,1))) | H16: =IF(OR($E16="",$G16=""),"",$G16-$E16)
A17: TH-10 | B17: Achados são convertidos na hierarquia de saídas: detecção automatizada > visibilidade > ... | C17: Hierarchy of detection outputs do PEAK. No HMM4, o hunt bem-sucedido vira detecção automática. | E17: =IF($D17="","",VALUE(LEFT($D17,1))) | G17: =IF($F17="","",VALUE(LEFT($F17,1))) | H17: =IF(OR($E17="",$G17=""),"",$G17-$E17)
A18: TH-11 | B18: Lacunas de visibilidade encontradas viram demandas de telemetria tratadas até o fim. | C18: Hunt que revela ponto cego deve gerar correção de coleta, não só anotação. | E18: =IF($D18="","",VALUE(LEFT($D18,1))) | G18: =IF($F18="","",VALUE(LEFT($F18,1))) | H18: =IF(OR($E18="",$G18=""),"",$G18-$E18)
A19: TH-12 | B19: Os resultados e o valor do programa são comunicados aos stakeholders. | C19: Fase Act inclui comunicação; mesmo hunts sem achado geram insight de ambiente. | E19: =IF($D19="","",VALUE(LEFT($D19,1))) | G19: =IF($F19="","",VALUE(LEFT($F19,1))) | H19: =IF(OR($E19="",$G19=""),"",$G19-$E19)
A20: MÉTRICAS · Medição do programa (HMM)
A21: TH-13 | B21: Métricas do programa são acompanhadas (hunts executados, achados, detecções criadas, lacunas). | C21: PEAK enfatiza métricas; incidentes abertos não são a única medida de sucesso. | E21: =IF($D21="","",VALUE(LEFT($D21,1))) | G21: =IF($F21="","",VALUE(LEFT($F21,1))) | H21: =IF(OR($E21="",$G21=""),"",$G21-$E21)
A22: TH-14 | B22: A maturidade do programa é avaliada periodicamente contra o HMM, com plano de evolução. | C22: O HMM serve de roadmap: escolha o nível-alvo e planeje as melhorias para alcançá-lo. | E22: =IF($D22="","",VALUE(LEFT($D22,1))) | G22: =IF($F22="","",VALUE(LEFT($F22,1))) | H22: =IF(OR($E22="",$G22=""),"",$G22-$E22)

Sheet Detection Eng
A1: DETECTION ENGINEERING — Maturity Matrix (Kyle Bailey)
A2: Detection Engineering Maturity Matrix · 3 pilares (Detection-as-Code, IR Experience, Detection Logic & Infrastructure) com subcategorias · escala 1–5.
A3: Como preencher: selecione o nível observado em "Avaliação atual" e o nível desejado em "Meta". As colunas Nível, Nível meta e Gap calculam automaticamente. Registre em "Evidências" o que sustenta a nota.
A4: ID | B4: Item de avaliação | C4: Orientação para o avaliador | D4: Avaliação atual | E4: Nível | F4: Meta (nível desejado) | G4: Nível meta | H4: Gap | I4: Evidências / observações | K4: MATURIDADE POR SUBDOMÍNIO
A5: Pilar 1 · DETECTION-AS-CODE | K5: Subdomínio | L5: Atual | M5: Meta
A6: DE-01 | B6: A lógica de detecção é versionada (version control para regras SIEM/EDR/Zeek/Suricata/YARA). | C6: Princípio central do pilar: tratar detecção como código. Versionamento responde "quando/por quem mudou?". | E6: =IF($D6="","",VALUE(LEFT($D6,1))) | G6: =IF($F6="","",VALUE(LEFT($F6,1))) | H6: =IF(OR($E6="",$G6=""),"",$G6-$E6) | K6: DETECTION-AS-CODE | L6: =IFERROR(AVERAGE($E$6:$E$9)/5,0) -> 0 | M6: =IFERROR(AVERAGE($G$6:$G$9)/5,0) -> 0
A7: DE-02 | B7: Há revisão e aprovação (peer review) antes do deploy da detecção. | C7: No nível 5, review e approval estão embutidos no pipeline. | E7: =IF($D7="","",VALUE(LEFT($D7,1))) | G7: =IF($F7="","",VALUE(LEFT($F7,1))) | H7: =IF(OR($E7="",$G7=""),"",$G7-$E7) | K7: INCIDENT RESPONSE EXPERIENCE | L7: =IFERROR(AVERAGE($E$11:$E$13)/5,0) -> 0 | M7: =IFERROR(AVERAGE($G$11:$G$13)/5,0) -> 0
A8: DE-03 | B8: Testes estático, dinâmico e contínuo estão embutidos no pipeline de deploy. | C8: Topo da matriz: "detection as code is engrained... static, dynamic and continuous testing baked into the pipeline". | E8: =IF($D8="","",VALUE(LEFT($D8,1))) | G8: =IF($F8="","",VALUE(LEFT($F8,1))) | H8: =IF(OR($E8="",$G8=""),"",$G8-$E8) | K8: DETECTION LOGIC & INFRASTRUCTURE | L8: =IFERROR(AVERAGE($E$15:$E$19)/5,0) -> 0 | M8: =IFERROR(AVERAGE($G$15:$G$19)/5,0) -> 0
A9: DE-04 | B9: Quase toda a lógica de detecção é testada continuamente de forma automatizada. | C9: Indicador de nível máximo do pilar Detection-as-Code. | E9: =IF($D9="","",VALUE(LEFT($D9,1))) | G9: =IF($F9="","",VALUE(LEFT($F9,1))) | H9: =IF(OR($E9="",$G9=""),"",$G9-$E9) | K9: EQUIPE & LIDERANÇA | L9: =IFERROR(AVERAGE($E$21:$E$22)/5,0) -> 0 | M9: =IFERROR(AVERAGE($G$21:$G$22)/5,0) -> 0
A10: Pilar 2 · INCIDENT RESPONSE EXPERIENCE
A11: DE-05 | B11: A detecção é desenhada considerando a experiência de quem responde (contexto, severidade, ação). | C11: Pilar IR Experience: a detecção existe para servir a resposta; alerta sem contexto gera fadiga. | E11: =IF($D11="","",VALUE(LEFT($D11,1))) | G11: =IF($F11="","",VALUE(LEFT($F11,1))) | H11: =IF(OR($E11="",$G11=""),"",$G11-$E11)
A12: DE-06 | B12: Cada detecção carrega metadados padronizados (técnica ATT&CK, severidade, dono, resposta esperada). | C12: Metadados consistentes aceleram triagem e permitem gestão de cobertura. | E12: =IF($D12="","",VALUE(LEFT($D12,1))) | G12: =IF($F12="","",VALUE(LEFT($F12,1))) | H12: =IF(OR($E12="",$G12=""),"",$G12-$E12)
A13: DE-07 | B13: O feedback da resposta (FP/FN) retroalimenta o tuning, com registro das mudanças. | C13: O ciclo de qualidade liga detecção e resposta; tuning sem registro perde a memória. | E13: =IF($D13="","",VALUE(LEFT($D13,1))) | G13: =IF($F13="","",VALUE(LEFT($F13,1))) | H13: =IF(OR($E13="",$G13=""),"",$G13-$E13)
A14: Pilar 3 · DETECTION LOGIC & INFRASTRUCTURE
A15: DE-08 | B15: A detecção define as fontes de log críticas e garante que estejam presentes no SIEM. | C15: Da matriz: "Detection defines critical log sources and ensures they are present in the SIEM". | E15: =IF($D15="","",VALUE(LEFT($D15,1))) | G15: =IF($F15="","",VALUE(LEFT($F15,1))) | H15: =IF(OR($E15="",$G15=""),"",$G15-$E15)
A16: DE-09 | B16: A saúde dos logs é monitorada e alertada (log health, erros de SIEM). | C16: Da matriz: "Log health is tracked and alerted on". Fonte que para vira ponto cego. | E16: =IF($D16="","",VALUE(LEFT($D16,1))) | G16: =IF($F16="","",VALUE(LEFT($F16,1))) | H16: =IF(OR($E16="",$G16=""),"",$G16-$E16)
A17: DE-10 | B17: A cobertura é mapeada e o KPI inclui cobertura ATT&CK por ambiente (Win, Mac, Corp, Prod). | C17: Da matriz: "KPIs are well defined to include applicable MITRE ATT&CK coverage per environment". | E17: =IF($D17="","",VALUE(LEFT($D17,1))) | G17: =IF($F17="","",VALUE(LEFT($F17,1))) | H17: =IF(OR($E17="",$G17=""),"",$G17-$E17)
A18: DE-11 | B18: As ameaças são emuladas (red/purple teaming ou emulação própria) para validar detecções. | C18: A matriz evolui de emulação pelos próprios engenheiros até red/purple teaming ativo. | E18: =IF($D18="","",VALUE(LEFT($D18,1))) | G18: =IF($F18="","",VALUE(LEFT($F18,1))) | H18: =IF(OR($E18="",$G18=""),"",$G18-$E18)
A19: DE-12 | B19: A detecção evolui de indicador para comportamento/TTP. | C19: Da matriz: "Detection is primarily indicator focused, few behavioral TTP detections exist" no nível baixo. | E19: =IF($D19="","",VALUE(LEFT($D19,1))) | G19: =IF($F19="","",VALUE(LEFT($F19,1))) | H19: =IF(OR($E19="",$G19=""),"",$G19-$E19)
A20: EQUIPE & LIDERANÇA
A21: DE-13 | B21: Existe equipe dedicada com SMEs definidos para todos os domínios (host, rede, app, nuvem). | C21: A matriz evolui de tarefa part-time do IR até equipe dedicada com ownership de domínio. | E21: =IF($D21="","",VALUE(LEFT($D21,1))) | G21: =IF($F21="","",VALUE(LEFT($F21,1))) | H21: =IF(OR($E21="",$G21=""),"",$G21-$E21)
A22: DE-14 | B22: A liderança patrocina a detecção (ferramentas, licenciamento, staffing) em toda a org. | C22: Topo da matriz: liderança advoga envolvimento em detecção por toda a organização. | E22: =IF($D22="","",VALUE(LEFT($D22,1))) | G22: =IF($F22="","",VALUE(LEFT($F22,1))) | H22: =IF(OR($E22="",$G22=""),"",$G22-$E22)

Sheet DFIR
A1: DFIR — CREST CSIR Maturity Assessment (15 passos / 3 fases)
A2: CREST Cyber Security Incident Response Maturity Assessment · 15 passos nas fases Prepare, Respond e Follow Up · escala 1 (menos eficaz) a 5 (mais eficaz).
A3: Como preencher: selecione o nível observado em "Avaliação atual" e o nível desejado em "Meta". As colunas Nível, Nível meta e Gap calculam automaticamente. Registre em "Evidências" o que sustenta a nota.
A4: ID | B4: Item de avaliação | C4: Orientação para o avaliador | D4: Avaliação atual | E4: Nível | F4: Meta (nível desejado) | G4: Nível meta | H4: Gap | I4: Evidências / observações | K4: MATURIDADE POR SUBDOMÍNIO
A5: Fase 1 · PREPARE | K5: Subdomínio | L5: Atual | M5: Meta
A6: IR-01 | B6: Passo 1 — Conduzir uma avaliação de criticidade da organização. | C6: Criticality assessment: identificar ativos/serviços mais críticos a proteger. Base de todas as fases seguintes. | E6: =IF($D6="","",VALUE(LEFT($D6,1))) | G6: =IF($F6="","",VALUE(LEFT($F6,1))) | H6: =IF(OR($E6="",$G6=""),"",$G6-$E6) | K6: PREPARE | L6: =IFERROR(AVERAGE($E$6:$E$10)/5,0) -> 0 | M6: =IFERROR(AVERAGE($G$6:$G$10)/5,0) -> 0
A7: IR-02 | B7: Passo 2 — Realizar análise de ameaças, apoiada por cenários realistas e ensaios. | C7: Threat analysis com cenários e rehearsals; alimenta o planejamento da resposta. | E7: =IF($D7="","",VALUE(LEFT($D7,1))) | G7: =IF($F7="","",VALUE(LEFT($F7,1))) | H7: =IF(OR($E7="",$G7=""),"",$G7-$E7) | K7: RESPOND | L7: =IFERROR(AVERAGE($E$12:$E$15)/5,0) -> 0 | M7: =IFERROR(AVERAGE($G$12:$G$15)/5,0) -> 0
A8: IR-03 | B8: Passo 3 — Considerar as implicações de pessoas, processo, tecnologia e informação. | C8: People/Process/Technology/Information: visão ampla da capacidade de resposta. | E8: =IF($D8="","",VALUE(LEFT($D8,1))) | G8: =IF($F8="","",VALUE(LEFT($F8,1))) | H8: =IF(OR($E8="",$G8=""),"",$G8-$E8) | K8: FOLLOW UP | L8: =IFERROR(AVERAGE($E$17:$E$22)/5,0) -> 0 | M8: =IFERROR(AVERAGE($G$17:$G$22)/5,0) -> 0
A9: IR-04 | B9: Passo 4 — Criar um ambiente de controle apropriado. | C9: Control environment: controles e governança que sustentam a resposta. | E9: =IF($D9="","",VALUE(LEFT($D9,1))) | G9: =IF($F9="","",VALUE(LEFT($F9,1))) | H9: =IF(OR($E9="",$G9=""),"",$G9-$E9)
A10: IR-05 | B10: Passo 5 — Revisar o estado de prontidão da resposta a incidentes. | C10: Maturity/readiness review: avaliar se a capacidade está pronta antes do incidente. | E10: =IF($D10="","",VALUE(LEFT($D10,1))) | G10: =IF($F10="","",VALUE(LEFT($F10,1))) | H10: =IF(OR($E10="",$G10=""),"",$G10-$E10)
A11: Fase 2 · RESPOND
A12: IR-06 | B12: Passo 1 — Identificar o incidente de segurança. | C12: Identification: detecção e qualificação do incidente a partir de IoCs. | E12: =IF($D12="","",VALUE(LEFT($D12,1))) | G12: =IF($F12="","",VALUE(LEFT($F12,1))) | H12: =IF(OR($E12="",$G12=""),"",$G12-$E12)
A13: IR-07 | B13: Passo 2 — Definir objetivos e investigar a situação. | C13: Investigation: estabelecer objetivos da resposta e entender o escopo do comprometimento. | E13: =IF($D13="","",VALUE(LEFT($D13,1))) | G13: =IF($F13="","",VALUE(LEFT($F13,1))) | H13: =IF(OR($E13="",$G13=""),"",$G13-$E13)
A14: IR-08 | B14: Passo 3 — Tomar a ação apropriada (contenção/erradicação). | C14: Action: conter e erradicar conforme a natureza do incidente. | E14: =IF($D14="","",VALUE(LEFT($D14,1))) | G14: =IF($F14="","",VALUE(LEFT($F14,1))) | H14: =IF(OR($E14="",$G14=""),"",$G14-$E14)
A15: IR-09 | B15: Passo 4 — Recuperar sistemas, dados e conectividade. | C15: Recovery: retorno seguro à operação normal. | E15: =IF($D15="","",VALUE(LEFT($D15,1))) | G15: =IF($F15="","",VALUE(LEFT($F15,1))) | H15: =IF(OR($E15="",$G15=""),"",$G15-$E15)
A16: Fase 3 · FOLLOW UP
A17: IR-10 | B17: Passo 1 — Investigar o incidente mais a fundo. | C17: Incident investigation: análise aprofundada de causa raiz pós-contenção. | E17: =IF($D17="","",VALUE(LEFT($D17,1))) | G17: =IF($F17="","",VALUE(LEFT($F17,1))) | H17: =IF(OR($E17="",$G17=""),"",$G17-$E17)
A18: IR-11 | B18: Passo 2 — Reportar o incidente aos stakeholders relevantes. | C18: Reporting: comunicação a partes interessadas e obrigações de notificação. | E18: =IF($D18="","",VALUE(LEFT($D18,1))) | G18: =IF($F18="","",VALUE(LEFT($F18,1))) | H18: =IF(OR($E18="",$G18=""),"",$G18-$E18)
A19: IR-12 | B19: Passo 3 — Realizar revisão pós-incidente. | C19: Post incident review: o post-mortem estruturado. | E19: =IF($D19="","",VALUE(LEFT($D19,1))) | G19: =IF($F19="","",VALUE(LEFT($F19,1))) | H19: =IF(OR($E19="",$G19=""),"",$G19-$E19)
A20: IR-13 | B20: Passo 4 — Comunicar e capitalizar as lições aprendidas. | C20: Lessons learned: transformar o incidente em melhoria concreta. | E20: =IF($D20="","",VALUE(LEFT($D20,1))) | G20: =IF($F20="","",VALUE(LEFT($F20,1))) | H20: =IF(OR($E20="",$G20=""),"",$G20-$E20)
A21: IR-14 | B21: Passo 5 — Atualizar informações, controles e processos-chave. | C21: Updating: refletir o aprendizado em documentos, controles e processos vivos. | E21: =IF($D21="","",VALUE(LEFT($D21,1))) | G21: =IF($F21="","",VALUE(LEFT($F21,1))) | H21: =IF(OR($E21="",$G21=""),"",$G21-$E21)
A22: IR-15 | B22: Passo 6 — Realizar análise de tendências. | C22: Trend analysis: cruzar incidentes ao longo do tempo para revelar padrões sistêmicos. | E22: =IF($D22="","",VALUE(LEFT($D22,1))) | G22: =IF($F22="","",VALUE(LEFT($F22,1))) | H22: =IF(OR($E22="",$G22=""),"",$G22-$E22)

Sheet CSIRT
A1: CSIRT — SIM3 v2 interim (45 parâmetros O/H/T/P)
A2: SIM3 v2 interim (Open CSIRT Foundation) · 4 quadrantes: Organisation (11), Human (7), Tools (10), Processes (17) · escala 0–4.
A3: Como preencher: selecione o nível observado em "Avaliação atual" e o nível desejado em "Meta". As colunas Nível, Nível meta e Gap calculam automaticamente. Registre em "Evidências" o que sustenta a nota.
A4: ID | B4: Item de avaliação | C4: Orientação para o avaliador | D4: Avaliação atual | E4: Nível | F4: Meta (nível desejado) | G4: Nível meta | H4: Gap | I4: Evidências / observações | K4: MATURIDADE POR SUBDOMÍNIO
A5: O · ORGANISATION (mandato, setup e serviços) | K5: Subdomínio | L5: Atual | M5: Meta
A6: CS-01 | B6: O-1 Mandate — a atribuição do CSIRT derivada de níveis de governança superiores. | C6: A justificativa da existência do time deve vir do mais alto nível de governança possível. | E6: =IF($D6="","",VALUE(LEFT($D6,1))) | G6: =IF($F6="","",VALUE(LEFT($F6,1))) | H6: =IF(OR($E6="",$G6=""),"",$G6-$E6) | K6: O · ORGANISATION | L6: =IFERROR(AVERAGE($E$6:$E$16)/4,0) -> 0 | M6: =IFERROR(AVERAGE($G$6:$G$16)/4,0) -> 0
A7: CS-02 | B7: O-2 Constituency — para quem o CSIRT trabalha (a base de "clientes"). | C7: Definir a constituency interna/externa atendida pelo time. | E7: =IF($D7="","",VALUE(LEFT($D7,1))) | G7: =IF($F7="","",VALUE(LEFT($F7,1))) | H7: =IF(OR($E7="",$G7=""),"",$G7-$E7) | K7: H · HUMAN | L7: =IFERROR(AVERAGE($E$18:$E$24)/4,0) -> 0 | M7: =IFERROR(AVERAGE($G$18:$G$24)/4,0) -> 0
A8: CS-03 | B8: O-3 Authority — o que o time tem permissão de fazer perante sua constituency. | C8: Os poderes investidos no CSIRT; vital em crises. Deve vir da governança superior. | E8: =IF($D8="","",VALUE(LEFT($D8,1))) | G8: =IF($F8="","",VALUE(LEFT($F8,1))) | H8: =IF(OR($E8="",$G8=""),"",$G8-$E8) | K8: T · TOOLS | L8: =IFERROR(AVERAGE($E$26:$E$35)/4,0) -> 0 | M8: =IFERROR(AVERAGE($G$26:$G$35)/4,0) -> 0
A9: CS-04 | B9: O-4 Responsibility — o que se espera que o time faça perante a constituency. | C9: Em geral a responsabilidade é maior que a autoridade; o gap não deve ser grande demais. | E9: =IF($D9="","",VALUE(LEFT($D9,1))) | G9: =IF($F9="","",VALUE(LEFT($F9,1))) | H9: =IF(OR($E9="",$G9=""),"",$G9-$E9) | K9: P · PROCESSES | L9: =IFERROR(AVERAGE($E$37:$E$53)/4,0) -> 0 | M9: =IFERROR(AVERAGE($G$37:$G$53)/4,0) -> 0
A10: CS-05 | B10: O-5 Service Description — descreve o que é o serviço do CSIRT e como acioná-lo. | C10: Recomenda-se RFC2350 público (inclusive em inglês) com contatos e janelas de serviço. | E10: =IF($D10="","",VALUE(LEFT($D10,1))) | G10: =IF($F10="","",VALUE(LEFT($F10,1))) | H10: =IF(OR($E10="",$G10=""),"",$G10-$E10)
A11: CS-06 | B11: O-6 Public Media Policy — política de interação com imprensa e mídias públicas. | C11: Parâmetro novo na v2 interim. Como lidar com imprensa e redes, inclusive em crise. | E11: =IF($D11="","",VALUE(LEFT($D11,1))) | G11: =IF($F11="","",VALUE(LEFT($F11,1))) | H11: =IF(OR($E11="",$G11=""),"",$G11-$E11)
A12: CS-07 | B12: O-7 Service Level Description — nível de serviço esperado do CSIRT. | C12: Inclui velocidade de reação a relatos (mín.: reação humana a pares em 2 dias úteis). | E12: =IF($D12="","",VALUE(LEFT($D12,1))) | G12: =IF($F12="","",VALUE(LEFT($F12,1))) | H12: =IF(OR($E12="",$G12=""),"",$G12-$E12)
A13: CS-08 | B13: O-8 Incident Classification — esquema de classificação de incidentes. | C13: Taxonomia de tipo/severidade/prioridade usada de forma consistente. | E13: =IF($D13="","",VALUE(LEFT($D13,1))) | G13: =IF($F13="","",VALUE(LEFT($F13,1))) | H13: =IF(OR($E13="",$G13=""),"",$G13-$E13)
A14: CS-09 | B14: O-9 Participation Policy — política de participação em comunidades/fóruns. | C14: Como e onde o time coopera (FIRST, TF-CSIRT, setoriais). | E14: =IF($D14="","",VALUE(LEFT($D14,1))) | G14: =IF($F14="","",VALUE(LEFT($F14,1))) | H14: =IF(OR($E14="",$G14=""),"",$G14-$E14)
A15: CS-10 | B15: O-10 Organisational Framework — charter/estrutura organizacional do time. | C15: Framework ou "team handbook" que conecta os aspectos organizacionais. | E15: =IF($D15="","",VALUE(LEFT($D15,1))) | G15: =IF($F15="","",VALUE(LEFT($F15,1))) | H15: =IF(OR($E15="",$G15=""),"",$G15-$E15)
A16: CS-11 | B16: O-11 Security Policy — política de segurança que rege a operação do CSIRT. | C16: O próprio time é alvo de alto valor; precisa de política aplicável a si. | E16: =IF($D16="","",VALUE(LEFT($D16,1))) | G16: =IF($F16="","",VALUE(LEFT($F16,1))) | H16: =IF(OR($E16="",$G16=""),"",$G16-$E16)
A17: H · HUMAN (pessoas)
A18: CS-12 | B18: H-1 Code of Conduct/Practice/Ethics — código de conduta/prática/ética do time. | C18: Base da confiança; pode usar TI CCoP ou EthicsFIRST como baseline. | E18: =IF($D18="","",VALUE(LEFT($D18,1))) | G18: =IF($F18="","",VALUE(LEFT($F18,1))) | H18: =IF(OR($E18="",$G18=""),"",$G18-$E18)
A19: CS-13 | B19: H-2 Personal Resilience — resiliência pessoal dos membros. | C19: Capacidade de operar sob pressão sustentada sem colapso. | E19: =IF($D19="","",VALUE(LEFT($D19,1))) | G19: =IF($F19="","",VALUE(LEFT($F19,1))) | H19: =IF(OR($E19="",$G19=""),"",$G19-$E19)
A20: CS-14 | B20: H-3 Skillset Description — descrição do conjunto de competências por função. | C20: Mapa de skills que orienta contratação e treinamento (alinha à doc de roles/competencies do FIRST). | E20: =IF($D20="","",VALUE(LEFT($D20,1))) | G20: =IF($F20="","",VALUE(LEFT($F20,1))) | H20: =IF(OR($E20="",$G20=""),"",$G20-$E20)
A21: CS-15 | B21: H-4 Internal Training — treinamento interno. | C21: Capacitação conduzida dentro do time/organização. | E21: =IF($D21="","",VALUE(LEFT($D21,1))) | G21: =IF($F21="","",VALUE(LEFT($F21,1))) | H21: =IF(OR($E21="",$G21=""),"",$G21-$E21)
A22: CS-16 | B22: H-5 (External) Technical Training — treinamento técnico externo. | C22: Capacitação técnica formal de fontes externas. | E22: =IF($D22="","",VALUE(LEFT($D22,1))) | G22: =IF($F22="","",VALUE(LEFT($F22,1))) | H22: =IF(OR($E22="",$G22=""),"",$G22-$E22)
A23: CS-17 | B23: H-6 (External) Communication Training — treinamento externo de comunicação. | C23: Comunicação e coordenação sob pressão são competências centrais do CSIRT. | E23: =IF($D23="","",VALUE(LEFT($D23,1))) | G23: =IF($F23="","",VALUE(LEFT($F23,1))) | H23: =IF(OR($E23="",$G23=""),"",$G23-$E23)
A24: CS-18 | B24: H-7 External Networking — relacionamento externo dos membros (networking). | C24: Rede de contatos com pares que acelera a resposta em incidentes cross-org. | E24: =IF($D24="","",VALUE(LEFT($D24,1))) | G24: =IF($F24="","",VALUE(LEFT($F24,1))) | H24: =IF(OR($E24="",$G24=""),"",$G24-$E24)
A25: T · TOOLS (ferramentas)
A26: CS-19 | B26: T-1 IT Resources List — inventário de recursos de TI do próprio time. | C26: O time precisa conhecer e gerir o próprio arsenal. | E26: =IF($D26="","",VALUE(LEFT($D26,1))) | G26: =IF($F26="","",VALUE(LEFT($F26,1))) | H26: =IF(OR($E26="",$G26=""),"",$G26-$E26)
A27: CS-20 | B27: T-2 Information Sources List — lista de fontes de informação. | C27: Avisos de fornecedores, vulnerabilidades e inteligência organizados para consumo. | E27: =IF($D27="","",VALUE(LEFT($D27,1))) | G27: =IF($F27="","",VALUE(LEFT($F27,1))) | H27: =IF(OR($E27="",$G27=""),"",$G27-$E27)
A28: CS-21 | B28: T-3 Consolidated E-mail System — sistema de e-mail consolidado do time. | C28: Caixa de equipe consolidada para os contatos do CSIRT. | E28: =IF($D28="","",VALUE(LEFT($D28,1))) | G28: =IF($F28="","",VALUE(LEFT($F28,1))) | H28: =IF(OR($E28="",$G28=""),"",$G28-$E28)
A29: CS-22 | B29: T-4 Incident Tracking System — sistema de registro/acompanhamento de incidentes. | C29: Tracker único dá rastreabilidade, histórico e base para métricas. | E29: =IF($D29="","",VALUE(LEFT($D29,1))) | G29: =IF($F29="","",VALUE(LEFT($F29,1))) | H29: =IF(OR($E29="",$G29=""),"",$G29-$E29)
A30: CS-23 | B30: T-5 Resilient Phone — telefonia resiliente. | C30: Canal de voz que sobrevive a indisponibilidades. | E30: =IF($D30="","",VALUE(LEFT($D30,1))) | G30: =IF($F30="","",VALUE(LEFT($F30,1))) | H30: =IF(OR($E30="",$G30=""),"",$G30-$E30)
A31: CS-24 | B31: T-6 Resilient E-mail — e-mail resiliente. | C31: E-mail que se mantém em cenários de degradação/comprometimento. | E31: =IF($D31="","",VALUE(LEFT($D31,1))) | G31: =IF($F31="","",VALUE(LEFT($F31,1))) | H31: =IF(OR($E31="",$G31=""),"",$G31-$E31)
A32: CS-25 | B32: T-7 Resilient Internet Access — acesso à Internet resiliente. | C32: Conectividade alternativa para operar durante incidentes. | E32: =IF($D32="","",VALUE(LEFT($D32,1))) | G32: =IF($F32="","",VALUE(LEFT($F32,1))) | H32: =IF(OR($E32="",$G32=""),"",$G32-$E32)
A33: CS-26 | B33: T-8 Incident Prevention Toolset — ferramentas de prevenção de incidentes. | C33: Pilar de prevenção do SIM (prevenção/detecção/resolução/feedback). | E33: =IF($D33="","",VALUE(LEFT($D33,1))) | G33: =IF($F33="","",VALUE(LEFT($F33,1))) | H33: =IF(OR($E33="",$G33=""),"",$G33-$E33)
A34: CS-27 | B34: T-9 Incident Detection Toolset — ferramentas de detecção de incidentes. | C34: Capacidade técnica de detectar a atividade adversária. | E34: =IF($D34="","",VALUE(LEFT($D34,1))) | G34: =IF($F34="","",VALUE(LEFT($F34,1))) | H34: =IF(OR($E34="",$G34=""),"",$G34-$E34)
A35: CS-28 | B35: T-10 Incident Resolution Toolset — ferramentas de resolução de incidentes. | C35: Capacidade técnica de conter, erradicar e recuperar. | E35: =IF($D35="","",VALUE(LEFT($D35,1))) | G35: =IF($F35="","",VALUE(LEFT($F35,1))) | H35: =IF(OR($E35="",$G35=""),"",$G35-$E35)
A36: P · PROCESSES (processos)
A37: CS-29 | B37: P-1 Escalation to Governance Level — escalonamento ao nível de governança. | C37: Quando e como acionar a governança superior. | E37: =IF($D37="","",VALUE(LEFT($D37,1))) | G37: =IF($F37="","",VALUE(LEFT($F37,1))) | H37: =IF(OR($E37="",$G37=""),"",$G37-$E37)
A38: CS-30 | B38: P-2 Escalation to Press Function — escalonamento à função de imprensa. | C38: Acionamento da comunicação/imprensa em incidentes. | E38: =IF($D38="","",VALUE(LEFT($D38,1))) | G38: =IF($F38="","",VALUE(LEFT($F38,1))) | H38: =IF(OR($E38="",$G38=""),"",$G38-$E38)
A39: CS-31 | B39: P-3 Escalation to Legal Function — escalonamento à função jurídica. | C39: Acionamento do jurídico no ciclo do incidente. | E39: =IF($D39="","",VALUE(LEFT($D39,1))) | G39: =IF($F39="","",VALUE(LEFT($F39,1))) | H39: =IF(OR($E39="",$G39=""),"",$G39-$E39)
A40: CS-32 | B40: P-4 Incident Prevention Process — processo de prevenção de incidentes. | C40: Pilar de prevenção formalizado como processo. | E40: =IF($D40="","",VALUE(LEFT($D40,1))) | G40: =IF($F40="","",VALUE(LEFT($F40,1))) | H40: =IF(OR($E40="",$G40=""),"",$G40-$E40)
A41: CS-33 | B41: P-5 Incident Detection Process — processo de detecção de incidentes. | C41: Como o time detecta de forma repetível. | E41: =IF($D41="","",VALUE(LEFT($D41,1))) | G41: =IF($F41="","",VALUE(LEFT($F41,1))) | H41: =IF(OR($E41="",$G41=""),"",$G41-$E41)
A42: CS-34 | B42: P-6 Incident Resolution Process — processo (genérico) de resolução de incidentes. | C42: O processo comum que garante o fluxo de tratamento de todos os incidentes. | E42: =IF($D42="","",VALUE(LEFT($D42,1))) | G42: =IF($F42="","",VALUE(LEFT($F42,1))) | H42: =IF(OR($E42="",$G42=""),"",$G42-$E42)
A43: CS-35 | B43: P-7 Specific Incident Processes — processos para tipos específicos de incidente. | C43: Processos dedicados aos tipos que causam mais trabalho (ex.: ransomware, DDoS). | E43: =IF($D43="","",VALUE(LEFT($D43,1))) | G43: =IF($F43="","",VALUE(LEFT($F43,1))) | H43: =IF(OR($E43="",$G43=""),"",$G43-$E43)
A44: CS-36 | B44: P-8 Audit & Feedback Process — processo de auditoria e feedback. | C44: Mecanismo de checagem/auditoria; essencial para parâmetros chegarem ao nível 4. | E44: =IF($D44="","",VALUE(LEFT($D44,1))) | G44: =IF($F44="","",VALUE(LEFT($F44,1))) | H44: =IF(OR($E44="",$G44=""),"",$G44-$E44)
A45: CS-37 | B45: P-9 Emergency Reachability Process — processo de alcançabilidade em emergência. | C45: Como o time é alcançado fora do horário/condições normais. | E45: =IF($D45="","",VALUE(LEFT($D45,1))) | G45: =IF($F45="","",VALUE(LEFT($F45,1))) | H45: =IF(OR($E45="",$G45=""),"",$G45-$E45)
A46: CS-38 | B46: P-10 Best Practice Internet Presence — presença na Internet conforme boas práticas. | C46: Presença pública segura e adequada do time. | E46: =IF($D46="","",VALUE(LEFT($D46,1))) | G46: =IF($F46="","",VALUE(LEFT($F46,1))) | H46: =IF(OR($E46="",$G46=""),"",$G46-$E46)
A47: CS-39 | B47: P-11 Secure Information Handling Process — manuseio seguro da informação. | C47: Classificação e tratamento seguro de dados sensíveis do incidente. | E47: =IF($D47="","",VALUE(LEFT($D47,1))) | G47: =IF($F47="","",VALUE(LEFT($F47,1))) | H47: =IF(OR($E47="",$G47=""),"",$G47-$E47)
A48: CS-40 | B48: P-12 Information Sources Process — processo das fontes de informação. | C48: Como as fontes (T-2) são processadas e usadas. | E48: =IF($D48="","",VALUE(LEFT($D48,1))) | G48: =IF($F48="","",VALUE(LEFT($F48,1))) | H48: =IF(OR($E48="",$G48=""),"",$G48-$E48)
... A53: CS-45 | B53: P-17 Peer-to-Peer / Collaboration Process — processo de colaboração com pares. | C53: Cooperação estruturada com outros times em incidentes cross-org. | E53: =IF($D53="","",VALUE(LEFT($D53,1))) | G53: =IF($F53="","",VALUE(LEFT($F53,1))) | H53: =IF(OR($E53="",$G53=""),"",$G53-$E53)

Sheet PSIRT
A1: PSIRT — FIRST PSIRT Services Framework (6 áreas de serviço)
A2: FIRST PSIRT Services Framework v1.1 · 6 áreas de serviço · maturidade conforme o PSIRT Maturity Document (básico→intermediário→avançado), escala 0–3.
A3: Como preencher: selecione o nível observado em "Avaliação atual" e o nível desejado em "Meta". As colunas Nível, Nível meta e Gap calculam automaticamente. Registre em "Evidências" o que sustenta a nota.
A4: ID | B4: Item de avaliação | C4: Orientação para o avaliador | D4: Avaliação atual | E4: Nível | F4: Meta (nível desejado) | G4: Nível meta | H4: Gap | I4: Evidências / observações | K4: MATURIDADE POR SUBDOMÍNIO
A5: Área 1 · Stakeholder Ecosystem Management | K5: Subdomínio | L5: Atual | M5: Meta
A6: PS-01 | B6: 1.1 Engajamento de stakeholders internos (engenharia, QA, release, suporte, jurídico). | C6: Stakeholders internos engajados fazem todos os processos do PSIRT fluírem melhor. | E6: =IF($D6="","",VALUE(LEFT($D6,1))) | G6: =IF($F6="","",VALUE(LEFT($F6,1))) | H6: =IF(OR($E6="",$G6=""),"",$G6-$E6) | K6: Stakeholder Ecosystem Management | L6: =IFERROR(AVERAGE($E$6:$E$9)/3,0) -> 0 | M6: =IFERROR(AVERAGE($G$6:$G$9)/3,0) -> 0
A7: PS-02 | B7: 1.2 Engajamento da comunidade e da organização (finders, pesquisadores). | C7: Engajamento direto com a comunidade de finders é marco de maturidade. | E7: =IF($D7="","",VALUE(LEFT($D7,1))) | G7: =IF($F7="","",VALUE(LEFT($F7,1))) | H7: =IF(OR($E7="",$G7=""),"",$G7-$E7) | K7: Vulnerability Discovery | L7: =IFERROR(AVERAGE($E$11:$E$13)/3,0) -> 0 | M7: =IFERROR(AVERAGE($G$11:$G$13)/3,0) -> 0
A8: PS-03 | B8: 1.3 Engajamento de upstream (componentes/projetos que você consome). | C8: Comunidade upstream ajuda em remediações complexas e supre expertise. | E8: =IF($D8="","",VALUE(LEFT($D8,1))) | G8: =IF($F8="","",VALUE(LEFT($F8,1))) | H8: =IF(OR($E8="",$G8=""),"",$G8-$E8) | K8: Vulnerability Triage & Analysis | L8: =IFERROR(AVERAGE($E$15:$E$17)/3,0) -> 0 | M8: =IFERROR(AVERAGE($G$15:$G$17)/3,0) -> 0
A9: PS-04 | B9: 1.4 Gestão de stakeholders downstream (quem consome seu produto). | C9: Downstream precisa ser notificado de forma coordenada. | E9: =IF($D9="","",VALUE(LEFT($D9,1))) | G9: =IF($F9="","",VALUE(LEFT($F9,1))) | H9: =IF(OR($E9="",$G9=""),"",$G9-$E9) | K9: Remediation | L9: =IFERROR(AVERAGE($E$19:$E$20)/3,0) -> 0 | M9: =IFERROR(AVERAGE($G$19:$G$20)/3,0) -> 0
A10: Área 2 · Vulnerability Discovery | K10: Disclosure | L10: =IFERROR(AVERAGE($E$22:$E$24)/3,0) -> 0 | M10: =IFERROR(AVERAGE($G$22:$G$24)/3,0) -> 0
A11: PS-05 | B11: 2.1 Recebimento de relatos de vulnerabilidade (ponto de contato, security.txt). | C11: Porta de entrada clara para relatos — base do nível básico. | E11: =IF($D11="","",VALUE(LEFT($D11,1))) | G11: =IF($F11="","",VALUE(LEFT($F11,1))) | H11: =IF(OR($E11="",$G11=""),"",$G11-$E11) | K11: Training & Education | L11: =IFERROR(AVERAGE($E$26:$E$28)/3,0) -> 0 | M11: =IFERROR(AVERAGE($G$26:$G$28)/3,0) -> 0
A12: PS-06 | B12: 2.2 Processo para descobrir vulnerabilidades não reportadas. | C12: Discovery proativo além do que chega espontaneamente. | E12: =IF($D12="","",VALUE(LEFT($D12,1))) | G12: =IF($F12="","",VALUE(LEFT($F12,1))) | H12: =IF(OR($E12="",$G12=""),"",$G12-$E12)
A13: PS-07 | B13: 2.3 Métricas de descoberta de vulnerabilidades (relatórios operacionais e de negócio). | C13: Operational e business reports da área de discovery. | E13: =IF($D13="","",VALUE(LEFT($D13,1))) | G13: =IF($F13="","",VALUE(LEFT($F13,1))) | H13: =IF(OR($E13="",$G13=""),"",$G13-$E13)
A14: Área 3 · Vulnerability Triage & Analysis
A15: PS-08 | B15: 3.1 Qualificação da vulnerabilidade (quality gate / bug bars). | C15: Critérios de qualificação e severidade aplicados de forma consistente. | E15: =IF($D15="","",VALUE(LEFT($D15,1))) | G15: =IF($F15="","",VALUE(LEFT($F15,1))) | H15: =IF(OR($E15="",$G15=""),"",$G15-$E15)
A16: PS-09 | B16: 3.2 Capacidade interna de reprodução da vulnerabilidade. | C16: Reproduzir internamente acelera e dá confiança à correção. | E16: =IF($D16="","",VALUE(LEFT($D16,1))) | G16: =IF($F16="","",VALUE(LEFT($F16,1))) | H16: =IF(OR($E16="",$G16=""),"",$G16-$E16)
A17: PS-10 | B17: 3.3 Melhoria contínua do processo de triagem. | C17: Continuous improvement da qualificação ao longo do tempo. | E17: =IF($D17="","",VALUE(LEFT($D17,1))) | G17: =IF($F17="","",VALUE(LEFT($F17,1))) | H17: =IF(OR($E17="",$G17=""),"",$G17-$E17)
A18: Área 4 · Remediation
A19: PS-11 | B19: 4.1 Plano formal de gestão do remédio de segurança (security remedy management). | C19: Formalizar o plano de remediação com os times de produto. | E19: =IF($D19="","",VALUE(LEFT($D19,1))) | G19: =IF($F19="","",VALUE(LEFT($F19,1))) | H19: =IF(OR($E19="",$G19=""),"",$G19-$E19)
A20: PS-12 | B20: 4.2 Coordenação da correção com engenharia e times de produto. | C20: PSIRT sem engenharia não remedia; o fluxo precisa de donos e janelas. | E20: =IF($D20="","",VALUE(LEFT($D20,1))) | G20: =IF($F20="","",VALUE(LEFT($F20,1))) | H20: =IF(OR($E20="",$G20=""),"",$G20-$E20)
A21: Área 5 · Disclosure
A22: PS-13 | B22: 5.1 Sistema de notificação de stakeholders sobre a vulnerabilidade. | C22: Criar sistema para notificar stakeholders na divulgação. | E22: =IF($D22="","",VALUE(LEFT($D22,1))) | G22: =IF($F22="","",VALUE(LEFT($F22,1))) | H22: =IF(OR($E22="",$G22=""),"",$G22-$E22)
A23: PS-14 | B23: 5.2 Advisories padronizados (versões afetadas, mitigação, identificadores). | C23: Comunicação clara reduz chamados e acelera correção; usar CVE quando aplicável. | E23: =IF($D23="","",VALUE(LEFT($D23,1))) | G23: =IF($F23="","",VALUE(LEFT($F23,1))) | H23: =IF(OR($E23="",$G23=""),"",$G23-$E23)
A24: PS-15 | B24: 5.3 Divulgação coordenada (CVD) com pesquisadores e ecossistema. | C24: Coordenar timelines e formatos de divulgação. | E24: =IF($D24="","",VALUE(LEFT($D24,1))) | G24: =IF($F24="","",VALUE(LEFT($F24,1))) | H24: =IF(OR($E24="",$G24=""),"",$G24-$E24)
A25: Área 6 · Training & Education
A26: PS-16 | B26: 6.1 Treinamento dos membros do PSIRT. | C26: Capacitar a própria equipe do PSIRT. | E26: =IF($D26="","",VALUE(LEFT($D26,1))) | G26: =IF($F26="","",VALUE(LEFT($F26,1))) | H26: =IF(OR($E26="",$G26=""),"",$G26-$E26)
A27: PS-17 | B27: 6.2 Mecanismos de feedback e integração ao ciclo de desenvolvimento (SDLC). | C27: No nível avançado o PSIRT se integra ao SDLC para prevenir recorrência. | E27: =IF($D27="","",VALUE(LEFT($D27,1))) | G27: =IF($F27="","",VALUE(LEFT($F27,1))) | H27: =IF(OR($E27="",$G27=""),"",$G27-$E27)
A28: PS-18 | B28: 6.3 Participação em comunidades do ecossistema (ex.: FIRST e SIGs). | C28: Comunidade traz prática consolidada e coordenação multifornecedor. | E28: =IF($D28="","",VALUE(LEFT($D28,1))) | G28: =IF($F28="","",VALUE(LEFT($F28,1))) | H28: =IF(OR($E28="",$G28=""),"",$G28-$E28)

Sheet Deception
A1: DECEPTION — MITRE Engage (Prepare · Expose · Affect · Elicit · Understand)
A2: MITRE Engage · 5 colunas da matriz (Prepare e Understand = estratégicas; Expose/Affect/Elicit = engajamento) + processo de 10 passos · escala adaptada 0–5.
A3: Como preencher: selecione o nível observado em "Avaliação atual" e o nível desejado em "Meta". As colunas Nível, Nível meta e Gap calculam automaticamente. Registre em "Evidências" o que sustenta a nota.
A4: ID | B4: Item de avaliação | C4: Orientação para o avaliador | D4: Avaliação atual | E4: Nível | F4: Meta (nível desejado) | G4: Nível meta | H4: Gap | I4: Evidências / observações | K4: MATURIDADE POR SUBDOMÍNIO
A5: PREPARE · planejamento estratégico (passos 1–6) | K5: Subdomínio | L5: Atual | M5: Meta
A6: DC-01 | B6: Os objetivos estratégicos do engajamento estão definidos (o que se quer Expor/Afetar/Elicitar). | C6: Goal Prepare do Engage: dirige toda a operação. Engajamento não é "fire and forget". | E6: =IF($D6="","",VALUE(LEFT($D6,1))) | G6: =IF($F6="","",VALUE(LEFT($F6,1))) | H6: =IF(OR($E6="",$G6=""),"",$G6-$E6) | K6: PREPARE | L6: =IFERROR(AVERAGE($E$6:$E$8)/5,0) -> 0 | M6: =IFERROR(AVERAGE($G$6:$G$8)/5,0) -> 0
A7: DC-02 | B7: Há análise de risco e aprovação para as operações de deception. | C7: Definir o que o adversário deve ver/pensar/fazer, com aval jurídico e da direção. | E7: =IF($D7="","",VALUE(LEFT($D7,1))) | G7: =IF($F7="","",VALUE(LEFT($F7,1))) | H7: =IF(OR($E7="",$G7=""),"",$G7-$E7) | K7: EXPOSE | L7: =IFERROR(AVERAGE($E$10:$E$11)/5,0) -> 0 | M7: =IFERROR(AVERAGE($G$10:$G$11)/5,0) -> 0
A8: DC-03 | B8: O ambiente de engajamento e a persona/narrativa são preparados de forma realista. | C8: Artefatos consistentes com o ambiente real; decoy identificável perde valor. | E8: =IF($D8="","",VALUE(LEFT($D8,1))) | G8: =IF($F8="","",VALUE(LEFT($F8,1))) | H8: =IF(OR($E8="",$G8=""),"",$G8-$E8) | K8: AFFECT | L8: =IFERROR(AVERAGE($E$13:$E$14)/5,0) -> 0 | M8: =IFERROR(AVERAGE($G$13:$G$14)/5,0) -> 0
A9: EXPOSE · expor o adversário | K9: ELICIT | L9: =IFERROR(AVERAGE($E$16:$E$17)/5,0) -> 0 | M9: =IFERROR(AVERAGE($G$16:$G$17)/5,0) -> 0
A10: DC-04 | B10: Artefatos de deception geram alertas de alta fidelidade quando tocados (decoys, honeytokens). | C10: Goal Expose: deception fornece alertas de altíssima fidelidade quando o adversário age. | E10: =IF($D10="","",VALUE(LEFT($D10,1))) | G10: =IF($F10="","",VALUE(LEFT($F10,1))) | H10: =IF(OR($E10="",$G10=""),"",$G10-$E10) | K10: UNDERSTAND | L10: =IFERROR(AVERAGE($E$19:$E$21)/5,0) -> 0 | M10: =IFERROR(AVERAGE($G$19:$G$21)/5,0) -> 0
A11: DC-05 | B11: Os artefatos cobrem múltiplas camadas e os caminhos de ataque relevantes (AD, ERP, backups). | C11: Posicionar iscas onde o adversário provável vai passar. | E11: =IF($D11="","",VALUE(LEFT($D11,1))) | G11: =IF($F11="","",VALUE(LEFT($F11,1))) | H11: =IF(OR($E11="",$G11=""),"",$G11-$E11)
A12: AFFECT · afetar o adversário
A13: DC-06 | B13: Atividades de Affect alteram a relação custo-valor do adversário (aumentar custo, reduzir valor). | C13: Goal Affect: impacto negativo nas operações do adversário. | E13: =IF($D13="","",VALUE(LEFT($D13,1))) | G13: =IF($F13="","",VALUE(LEFT($F13,1))) | H13: =IF(OR($E13="",$G13=""),"",$G13-$E13)
A14: DC-07 | B14: Há controle para direcionar o adversário para longe de sistemas vulneráveis (ex.: legados). | C14: Exemplo do Engage: usar decoys para desviar de sistemas que não podem ser corrigidos. | E14: =IF($D14="","",VALUE(LEFT($D14,1))) | G14: =IF($F14="","",VALUE(LEFT($F14,1))) | H14: =IF(OR($E14="",$G14=""),"",$G14-$E14)
A15: ELICIT · elicitar informação
A16: DC-08 | B16: Atividades de Elicit observam o adversário para aprender TTPs (gerar CTI própria). | C16: Goal Elicit: gerar feed de CTI dirigido pelos TTPs do adversário, não pelo "CVE do dia". | E16: =IF($D16="","",VALUE(LEFT($D16,1))) | G16: =IF($F16="","",VALUE(LEFT($F16,1))) | H16: =IF(OR($E16="",$G16=""),"",$G16-$E16)
A17: DC-09 | B17: A telemetria do adversário é capturada e analisada de forma estruturada. | C17: O grande subproduto é inteligência de primeira mão sobre quem ataca o ambiente. | E17: =IF($D17="","",VALUE(LEFT($D17,1))) | G17: =IF($F17="","",VALUE(LEFT($F17,1))) | H17: =IF(OR($E17="",$G17=""),"",$G17-$E17)
A18: UNDERSTAND · análise estratégica (passos 8–10)
A19: DC-10 | B19: Os resultados das operações são analisados (output) e alimentam a estratégia. | C19: Goal Understand: fechar o ciclo entendendo os resultados das ações operacionais. | E19: =IF($D19="","",VALUE(LEFT($D19,1))) | G19: =IF($F19="","",VALUE(LEFT($F19,1))) | H19: =IF(OR($E19="",$G19=""),"",$G19-$E19)
A20: DC-11 | B20: Alertas de deception chegam ao SOC como eventos prioritários com playbook próprio. | C20: Toque em decoy deve furar a fila; decidir antes se a postura é observar ou conter. | E20: =IF($D20="","",VALUE(LEFT($D20,1))) | G20: =IF($F20="","",VALUE(LEFT($F20,1))) | H20: =IF(OR($E20="",$G20=""),"",$G20-$E20)
A21: DC-12 | B21: O aprendizado vira detecções, regras e inteligência para o restante da defesa. | C21: O que a isca ensinou deve proteger o ambiente real. | E21: =IF($D21="","",VALUE(LEFT($D21,1))) | G21: =IF($F21="","",VALUE(LEFT($F21,1))) | H21: =IF(OR($E21="",$G21=""),"",$G21-$E21)

Sheet Vuln Mgmt
A1: GESTÃO DE VULNERABILIDADES — SANS VMMM (ciclo PIACT)
A2: SANS Vulnerability Management Maturity Model · 5 domínios PIACT (Prepare/Identify/Analyze/Communicate/Treat) com subáreas · níveis 1 Initial → 5 Optimizing.
A3: Como preencher: selecione o nível observado em "Avaliação atual" e o nível desejado em "Meta". As colunas Nível, Nível meta e Gap calculam automaticamente. Registre em "Evidências" o que sustenta a nota.
A4: ID | B4: Item de avaliação | C4: Orientação para o avaliador | D4: Avaliação atual | E4: Nível | F4: Meta (nível desejado) | G4: Nível meta | H4: Gap | I4: Evidências / observações | K4: MATURIDADE POR SUBDOMÍNIO
A5: PREPARE | K5: Subdomínio | L5: Atual | M5: Meta
A6: VM-01 | B6: Política e padrões de VM definidos, alinhados a frameworks reconhecidos. | C6: Subárea Policy: do nível 1 (sem política) ao 5 (alinhada a frameworks e automatizada por controles). | E6: =IF($D6="","",VALUE(LEFT($D6,1))) | G6: =IF($F6="","",VALUE(LEFT($F6,1))) | H6: =IF(OR($E6="",$G6=""),"",$G6-$E6) | K6: PREPARE | L6: =IFERROR(AVERAGE($E$6:$E$8)/5,0) -> 0 | M6: =IFERROR(AVERAGE($G$6:$G$8)/5,0) -> 0
A7: VM-02 | B7: Contexto de negócio e papéis/responsabilidades acordados entre segurança e donos de ativos. | C7: Quem encontra não é quem corrige; o fluxo entre as partes precisa estar pactuado. | E7: =IF($D7="","",VALUE(LEFT($D7,1))) | G7: =IF($F7="","",VALUE(LEFT($F7,1))) | H7: =IF(OR($E7="",$G7=""),"",$G7-$E7) | K7: IDENTIFY | L7: =IFERROR(AVERAGE($E$10:$E$12)/5,0) -> 0 | M7: =IFERROR(AVERAGE($G$10:$G$12)/5,0) -> 0
A8: VM-03 | B8: Inventário de ativos com criticidade e exposição sustenta a priorização. | C8: Sem contexto de ativo não há priorização real por risco. | E8: =IF($D8="","",VALUE(LEFT($D8,1))) | G8: =IF($F8="","",VALUE(LEFT($F8,1))) | H8: =IF(OR($E8="",$G8=""),"",$G8-$E8) | K8: ANALYZE | L8: =IFERROR(AVERAGE($E$14:$E$16)/5,0) -> 0 | M8: =IFERROR(AVERAGE($G$14:$G$16)/5,0) -> 0
A9: IDENTIFY | K9: COMMUNICATE | L9: =IFERROR(AVERAGE($E$18:$E$20)/5,0) -> 0 | M9: =IFERROR(AVERAGE($G$18:$G$20)/5,0) -> 0
A10: VM-04 | B10: Identificação automatizada (scanning de infra e aplicações) definida e seguida. | C10: Categoria automated do Identify: do scan ad-hoc ao processo definido e seguido por área. | E10: =IF($D10="","",VALUE(LEFT($D10,1))) | G10: =IF($F10="","",VALUE(LEFT($F10,1))) | H10: =IF(OR($E10="",$G10=""),"",$G10-$E10) | K10: TREAT | L10: =IFERROR(AVERAGE($E$22:$E$24)/5,0) -> 0 | M10: =IFERROR(AVERAGE($G$22:$G$24)/5,0) -> 0
A11: VM-05 | B11: Identificação manual complementa a automatizada onde necessário. | C11: Categoria manual do Identify. | E11: =IF($D11="","",VALUE(LEFT($D11,1))) | G11: =IF($F11="","",VALUE(LEFT($F11,1))) | H11: =IF(OR($E11="",$G11=""),"",$G11-$E11)
A12: VM-06 | B12: Identificação externa (pentest, bug bounty, pesquisa) com metas e campanhas. | C12: Categoria external: do esporádico a um programa maduro com goals e campanhas. | E12: =IF($D12="","",VALUE(LEFT($D12,1))) | G12: =IF($F12="","",VALUE(LEFT($F12,1))) | H12: =IF(OR($E12="",$G12=""),"",$G12-$E12)
A13: ANALYZE
A14: VM-07 | B14: Priorização combina severidade, exploração ativa, exposição e criticidade do ativo. | C14: Usar KEV/EPSS + contexto; CVSS isolado gera fila infinita. | E14: =IF($D14="","",VALUE(LEFT($D14,1))) | G14: =IF($F14="","",VALUE(LEFT($F14,1))) | H14: =IF(OR($E14="",$G14=""),"",$G14-$E14)
A15: VM-08 | B15: Achados são validados e deduplicados antes do encaminhamento. | C15: Falsos positivos encaminhados minam a credibilidade do programa. | E15: =IF($D15="","",VALUE(LEFT($D15,1))) | G15: =IF($F15="","",VALUE(LEFT($F15,1))) | H15: =IF(OR($E15="",$G15=""),"",$G15-$E15)
A16: VM-09 | B16: Análise identifica causas recorrentes (padrões por tecnologia/time/processo). | C16: Tratar a causa raiz reduz o fluxo de novos achados. | E16: =IF($D16="","",VALUE(LEFT($D16,1))) | G16: =IF($F16="","",VALUE(LEFT($F16,1))) | H16: =IF(OR($E16="",$G16=""),"",$G16-$E16)
A17: COMMUNICATE
A18: VM-10 | B18: Métricas e relatórios adequados a cada público (do operacional ao executivo). | C18: Subárea metrics & reporting: do ponto-no-tempo bruto ao correlacionado com política/compliance. | E18: =IF($D18="","",VALUE(LEFT($D18,1))) | G18: =IF($F18="","",VALUE(LEFT($F18,1))) | H18: =IF(OR($E18="",$G18=""),"",$G18-$E18)
A19: VM-11 | B19: Alerting definido para achados que exigem ação imediata. | C19: Subárea alerting: do inexistente ao alerta automatizado e direcionado. | E19: =IF($D19="","",VALUE(LEFT($D19,1))) | G19: =IF($F19="","",VALUE(LEFT($F19,1))) | H19: =IF(OR($E19="",$G19=""),"",$G19-$E19)
A20: VM-12 | B20: Os achados chegam aos donos certos com clareza da ação esperada. | C20: Encaminhamento sem dono e sem ação clara não vira correção. | E20: =IF($D20="","",VALUE(LEFT($D20,1))) | G20: =IF($F20="","",VALUE(LEFT($F20,1))) | H20: =IF(OR($E20="",$G20=""),"",$G20-$E20)
A21: TREAT
A22: VM-13 | B22: Fluxo de remediação/mitigação gerido até a conclusão, com reteste. | C22: O reteste confirma que a correção fechou a exposição. | E22: =IF($D22="","",VALUE(LEFT($D22,1))) | G22: =IF($F22="","",VALUE(LEFT($F22,1))) | H22: =IF(OR($E22="",$G22=""),"",$G22-$E22)
A23: VM-14 | B23: Exceções com aceite de risco formal e validade definida. | C23: Exceção sem prazo de revisão é risco permanente disfarçado. | E23: =IF($D23="","",VALUE(LEFT($D23,1))) | G23: =IF($F23="","",VALUE(LEFT($F23,1))) | H23: =IF(OR($E23="",$G23=""),"",$G23-$E23)
A24: VM-15 | B24: Desempenho do tratamento medido e usado para melhorar o programa. | C24: Tendência de envelhecimento dos achados revela a saúde do ciclo. | E24: =IF($D24="","",VALUE(LEFT($D24,1))) | G24: =IF($F24="","",VALUE(LEFT($F24,1))) | H24: =IF(OR($E24="",$G24=""),"",$G24-$E24)

Sheet Automacao
A1: AUTOMAÇÃO & ORQUESTRAÇÃO (SOAR)
A2: Adaptado do aspecto Automation & Orchestration do SOC-CMM (domínio Technology) e da dimensão de disseminação do INFORM (MITRE CTID) · escala 0–5.
A3: Como preencher: selecione o nível observado em "Avaliação atual" e o nível desejado em "Meta". As colunas Nível, Nível meta e Gap calculam automaticamente. Registre em "Evidências" o que sustenta a nota.
A4: ID | B4: Item de avaliação | C4: Orientação para o avaliador | D4: Avaliação atual | E4: Nível | F4: Meta (nível desejado) | G4: Nível meta | H4: Gap | I4: Evidências / observações | K4: MATURIDADE POR SUBDOMÍNIO
A5: Estratégia & casos de uso | K5: Subdomínio | L5: Atual | M5: Meta
A6: AU-01 | B6: Casos de uso de automação priorizados por ganho e esforço, em backlog vivo. | C6: Automatize primeiro o repetitivo e frequente. | E6: =IF($D6="","",VALUE(LEFT($D6,1))) | G6: =IF($F6="","",VALUE(LEFT($F6,1))) | H6: =IF(OR($E6="",$G6=""),"",$G6-$E6) | K6: Estratégia & casos de uso | L6: =IFERROR(AVERAGE($E$6:$E$8)/5,0) -> 0 | M6: =IFERROR(AVERAGE($G$6:$G$8)/5,0) -> 0
A7: AU-02 | B7: Processos padronizados antes de serem automatizados. | C7: Automatizar caos só acelera o caos. | E7: =IF($D7="","",VALUE(LEFT($D7,1))) | G7: =IF($F7="","",VALUE(LEFT($F7,1))) | H7: =IF(OR($E7="",$G7=""),"",$G7-$E7) | K7: Implementação & integrações | L7: =IFERROR(AVERAGE($E$10:$E$12)/5,0) -> 0 | M7: =IFERROR(AVERAGE($G$10:$G$12)/5,0) -> 0
A8: AU-03 | B8: Responsável definido pela plataforma e pelo ciclo de vida das automações. | C8: Automação órfã quebra silenciosamente e mina a confiança. | E8: =IF($D8="","",VALUE(LEFT($D8,1))) | G8: =IF($F8="","",VALUE(LEFT($F8,1))) | H8: =IF(OR($E8="",$G8=""),"",$G8-$E8) | K8: Operação & medição | L8: =IFERROR(AVERAGE($E$14:$E$16)/5,0) -> 0 | M8: =IFERROR(AVERAGE($G$14:$G$16)/5,0) -> 0
A9: Implementação & integrações
A10: AU-04 | B10: Plataforma central (SOAR/middleware, ex.: n8n, Shuffle) integra o ecossistema. | C10: Integração ponto a ponto não escala; centralize o barramento. | E10: =IF($D10="","",VALUE(LEFT($D10,1))) | G10: =IF($F10="","",VALUE(LEFT($F10,1))) | H10: =IF(OR($E10="",$G10=""),"",$G10-$E10)
A11: AU-05 | B11: Playbooks tratam erros e incluem aprovação humana em ações sensíveis. | C11: Falha silenciosa e ação destrutiva sem aprovação são os dois grandes riscos. | E11: =IF($D11="","",VALUE(LEFT($D11,1))) | G11: =IF($F11="","",VALUE(LEFT($F11,1))) | H11: =IF(OR($E11="",$G11=""),"",$G11-$E11)
A12: AU-06 | B12: Automações versionadas, documentadas e testadas antes da produção. | C12: Trate playbooks como código: review, versionamento, rollback. | E12: =IF($D12="","",VALUE(LEFT($D12,1))) | G12: =IF($F12="","",VALUE(LEFT($F12,1))) | H12: =IF(OR($E12="",$G12=""),"",$G12-$E12)
A13: Operação & medição
A14: AU-07 | B14: Execução monitorada (sucesso, falha, fila, latência). | C14: É preciso saber imediatamente quando a automação parou. | E14: =IF($D14="","",VALUE(LEFT($D14,1))) | G14: =IF($F14="","",VALUE(LEFT($F14,1))) | H14: =IF(OR($E14="",$G14=""),"",$G14-$E14)
A15: AU-08 | B15: Ganho medido (tempo poupado, consistência, volume absorvido). | C15: Medir o retorno orienta a próxima onda. | E15: =IF($D15="","",VALUE(LEFT($D15,1))) | G15: =IF($F15="","",VALUE(LEFT($F15,1))) | H15: =IF(OR($E15="",$G15=""),"",$G15-$E15)
A16: AU-09 | B16: Ciclo de melhoria e expansão contínua do portfólio. | C16: Revisões aposentam o obsoleto e ampliam o que funciona. | E16: =IF($D16="","",VALUE(LEFT($D16,1))) | G16: =IF($F16="","",VALUE(LEFT($F16,1))) | H16: =IF(OR($E16="",$G16=""),"",$G16-$E16)

Sheet Dash
A1: DASH — Maturidade dos Domínios do SOC (versão completa)
A2: Consolidação automática · escalas normalizadas em % · radar por domínio e detalhe por categoria
A4: MATURIDADE GERAL (média das categorias) | B4: =$E$63 -> 0 | D4: =IF($B$4<0.1,"Inexistente — capacidade ausente",IF($B$4<0.3,"Inicial — práticas ad hoc",IF($B$4<0.5,"Em desenvolvimento — repetível",IF($B$4<0.7,"Definido — padronizado",IF($B$4<0.9,"Gerenciado — medido","Otimizado — melhoria contínua"))))) -> Inexistente — capacidade ausente
A7: Resultado por categoria
A8: Categoria | B8: Nível atual | C8: Nível meta | D8: Gap | E8: Maturidade atual | F8: Maturidade meta | G8: Escala
A9: ▍ CTI
A10: PROGRAM | B10: =IFERROR(AVERAGE(CTI!$E$6:$E$8),0) -> 0 | C10: =IFERROR(AVERAGE(CTI!$G$6:$G$8),0) -> 0 | D10: =$C10-$B10 -> 0 | E10: =$B10/3 -> 0 | F10: =$C10/3 -> 0 | G10: 0–3
A11: ASSET | B11: =IFERROR(AVERAGE(CTI!$E$10:$E$11),0) -> 0 | C11: =IFERROR(AVERAGE(CTI!$G$10:$G$11),0) -> 0 | D11: =$C11-$B11 -> 0 | E11: =$B11/3 -> 0 | F11: =$C11/3 -> 0 | G11: 0–3
A12: THREAT | B12: =IFERROR(AVERAGE(CTI!$E$13:$E$15),0) -> 0 | C12: =IFERROR(AVERAGE(CTI!$G$13:$G$15),0) -> 0 | D12: =$C12-$B12 -> 0 | E12: =$B12/3 -> 0 | F12: =$C12/3 -> 0 | G12: 0–3
A13: RISK | B13: =IFERROR(AVERAGE(CTI!$E$17:$E$18),0) -> 0 | C13: =IFERROR(AVERAGE(CTI!$G$17:$G$18),0) -> 0 | D13: =$C13-$B13 -> 0 | E13: =$B13/3 -> 0 | F13: =$C13/3 -> 0 | G13: 0–3
A14: SITUATION | B14: =IFERROR(AVERAGE(CTI!$E$20:$E$21),0) -> 0 | C14: =IFERROR(AVERAGE(CTI!$G$20:$G$21),0) -> 0 | D14: =$C14-$B14 -> 0 | E14: =$B14/3 -> 0 | F14: =$C14/3 -> 0 | G14: 0–3
A15: RESPONSE | B15: =IFERROR(AVERAGE(CTI!$E$23:$E$24),0) -> 0 | C15: =IFERROR(AVERAGE(CTI!$G$23:$G$24),0) -> 0 | D15: =$C15-$B15 -> 0 | E15: =$B15/3 -> 0 | F15: =$C15/3 -> 0 | G15: 0–3
A16: ACCESS | B16: =IFERROR(AVERAGE(CTI!$E$26:$E$27),0) -> 0 | C16: =IFERROR(AVERAGE(CTI!$G$26:$G$27),0) -> 0 | D16: =$C16-$B16 -> 0 | E16: =$B16/3 -> 0 | F16: =$C16/3 -> 0 | G16: 0–3
A17: WORKFORCE | B17: =IFERROR(AVERAGE(CTI!$E$29:$E$30),0) -> 0 | C17: =IFERROR(AVERAGE(CTI!$G$29:$G$30),0) -> 0 | D17: =$C17-$B17 -> 0 | E17: =$B17/3 -> 0 | F17: =$C17/3 -> 0 | G17: 0–3
A18: ARCHITECTURE | B18: =IFERROR(AVERAGE(CTI!$E$32:$E$33),0) -> 0 | C18: =IFERROR(AVERAGE(CTI!$G$32:$G$33),0) -> 0 | D18: =$C18-$B18 -> 0 | E18: =$B18/3 -> 0 | F18: =$C18/3 -> 0 | G18: 0–3
A19: THIRD-PARTIES | B19: =IFERROR(AVERAGE(CTI!$E$35:$E$36),0) -> 0 | C19: =IFERROR(AVERAGE(CTI!$G$35:$G$36),0) -> 0 | D19: =$C19-$B19 -> 0 | E19: =$B19/3 -> 0 | F19: =$C19/3 -> 0 | G19: 0–3
A20: FRAUD | B20: =IFERROR(AVERAGE(CTI!$E$38:$E$39),0) -> 0 | C20: =IFERROR(AVERAGE(CTI!$G$38:$G$39),0) -> 0 | D20: =$C20-$B20 -> 0 | E20: =$B20/3 -> 0 | F20: =$C20/3 -> 0 | G20: 0–3
A21: ▍ Threat Hunting
A22: PREPARE | B22: =IFERROR(AVERAGE('Threat Hunting'!$E$6:$E$9),0) -> 0 | C22: =IFERROR(AVERAGE('Threat Hunting'!$G$6:$G$9),0) -> 0 | D22: =$C22-$B22 -> 0 | E22: =$B22/4 -> 0 | F22: =$C22/4 -> 0 | G22: 0–4
A23: EXECUTE | B23: =IFERROR(AVERAGE('Threat Hunting'!$E$11:$E$14),0) -> 0 | C23: =IFERROR(AVERAGE('Threat Hunting'!$G$11:$G$14),0) -> 0 | D23: =$C23-$B23 -> 0 | E23: =$B23/4 -> 0 | F23: =$C23/4 -> 0 | G23: 0–4
A24: ACT · Documentação, | B24: =IFERROR(AVERAGE('Threat Hunting'!$E$16:$E$19),0) -> 0 | C24: =IFERROR(AVERAGE('Threat Hunting'!$G$16:$G$19),0) -> 0 | D24: =$C24-$B24 -> 0 | E24: =$B24/4 -> 0 | F24: =$C24/4 -> 0 | G24: 0–4
A25: MÉTRICAS | B25: =IFERROR(AVERAGE('Threat Hunting'!$E$21:$E$22),0) -> 0 | C25: =IFERROR(AVERAGE('Threat Hunting'!$G$21:$G$22),0) -> 0 | D25: =$C25-$B25 -> 0 | E25: =$B25/4 -> 0 | F25: =$C25/4 -> 0 | G25: 0–4
A26: ▍ Detection Engineering
A27: DETECTION-AS-CODE | B27: =IFERROR(AVERAGE('Detection Eng'!$E$6:$E$9),0) -> 0 | C27: =IFERROR(AVERAGE('Detection Eng'!$G$6:$G$9),0) -> 0 | D27: =$C27-$B27 -> 0 | E27: =$B27/5 -> 0 | F27: =$C27/5 -> 0 | G27: 1–5
A28: INCIDENT RESPONSE EXPERIENCE | B28: =IFERROR(AVERAGE('Detection Eng'!$E$11:$E$13),0) -> 0 | C28: =IFERROR(AVERAGE('Detection Eng'!$G$11:$G$13),0) -> 0 | D28: =$C28-$B28 -> 0 | E28: =$B28/5 -> 0 | F28: =$C28/5 -> 0 | G28: 1–5
A29: DETECTION LOGIC & INFRASTRUCTURE | B29: =IFERROR(AVERAGE('Detection Eng'!$E$15:$E$19),0) -> 0 | C29: =IFERROR(AVERAGE('Detection Eng'!$G$15:$G$19),0) -> 0 | D29: =$C29-$B29 -> 0 | E29: =$B29/5 -> 0 | F29: =$C29/5 -> 0 | G29: 1–5
A30: EQUIPE & LIDERANÇA | B30: =IFERROR(AVERAGE('Detection Eng'!$E$21:$E$22),0) -> 0 | C30: =IFERROR(AVERAGE('Detection Eng'!$G$21:$G$22),0) -> 0 | D30: =$C30-$B30 -> 0 | E30: =$B30/5 -> 0 | F30: =$C30/5 -> 0 | G30: 1–5
A31: ▍ DFIR / Resposta a Incidentes
A32: PREPARE | B32: =IFERROR(AVERAGE(DFIR!$E$6:$E$10),0) -> 0 | C32: =IFERROR(AVERAGE(DFIR!$G$6:$G$10),0) -> 0 | D32: =$C32-$B32 -> 0 | E32: =$B32/5 -> 0 | F32: =$C32/5 -> 0 | G32: 1–5
A33: RESPOND | B33: =IFERROR(AVERAGE(DFIR!$E$12:$E$15),0) -> 0 | C33: =IFERROR(AVERAGE(DFIR!$G$12:$G$15),0) -> 0 | D33: =$C33-$B33 -> 0 | E33: =$B33/5 -> 0 | F33: =$C33/5 -> 0 | G33: 1–5
A34: FOLLOW UP | B34: =IFERROR(AVERAGE(DFIR!$E$17:$E$22),0) -> 0 | C34: =IFERROR(AVERAGE(DFIR!$G$17:$G$22),0) -> 0 | D34: =$C34-$B34 -> 0 | E34: =$B34/5 -> 0 | F34: =$C34/5 -> 0 | G34: 1–5
A35: ▍ CSIRT
A36: O · ORGANISATION | B36: =IFERROR(AVERAGE(CSIRT!$E$6:$E$16),0) -> 0 | C36: =IFERROR(AVERAGE(CSIRT!$G$6:$G$16),0) -> 0 | D36: =$C36-$B36 -> 0 | E36: =$B36/4 -> 0 | F36: =$C36/4 -> 0 | G36: 0–4
A37: H · HUMAN | B37: =IFERROR(AVERAGE(CSIRT!$E$18:$E$24),0) -> 0 | C37: =IFERROR(AVERAGE(CSIRT!$G$18:$G$24),0) -> 0 | D37: =$C37-$B37 -> 0 | E37: =$B37/4 -> 0 | F37: =$C37/4 -> 0 | G37: 0–4
A38: T · TOOLS | B38: =IFERROR(AVERAGE(CSIRT!$E$26:$E$35),0) -> 0 | C38: =IFERROR(AVERAGE(CSIRT!$G$26:$G$35),0) -> 0 | D38: =$C38-$B38 -> 0 | E38: =$B38/4 -> 0 | F38: =$C38/4 -> 0 | G38: 0–4
A39: P · PROCESSES | B39: =IFERROR(AVERAGE(CSIRT!$E$37:$E$53),0) -> 0 | C39: =IFERROR(AVERAGE(CSIRT!$G$37:$G$53),0) -> 0 | D39: =$C39-$B39 -> 0 | E39: =$B39/4 -> 0 | F39: =$C39/4 -> 0 | G39: 0–4
A40: ▍ PSIRT
A41: Stakeholder Ecosystem Management | B41: =IFERROR(AVERAGE(PSIRT!$E$6:$E$9),0) -> 0 | C41: =IFERROR(AVERAGE(PSIRT!$G$6:$G$9),0) -> 0 | D41: =$C41-$B41 -> 0 | E41: =$B41/3 -> 0 | F41: =$C41/3 -> 0 | G41: 0–3
A42: Vulnerability Discovery | B42: =IFERROR(AVERAGE(PSIRT!$E$11:$E$13),0) -> 0 | C42: =IFERROR(AVERAGE(PSIRT!$G$11:$G$13),0) -> 0 | D42: =$C42-$B42 -> 0 | E42: =$B42/3 -> 0 | F42: =$C42/3 -> 0 | G42: 0–3
A43: Vulnerability Triage & Analysis | B43: =IFERROR(AVERAGE(PSIRT!$E$15:$E$17),0) -> 0 | C43: =IFERROR(AVERAGE(PSIRT!$G$15:$G$17),0) -> 0 | D43: =$C43-$B43 -> 0 | E43: =$B43/3 -> 0 | F43: =$C43/3 -> 0 | G43: 0–3
A44: Remediation | B44: =IFERROR(AVERAGE(PSIRT!$E$19:$E$20),0) -> 0 | C44: =IFERROR(AVERAGE(PSIRT!$G$19:$G$20),0) -> 0 | D44: =$C44-$B44 -> 0 | E44: =$B44/3 -> 0 | F44: =$C44/3 -> 0 | G44: 0–3
A45: Disclosure | B45: =IFERROR(AVERAGE(PSIRT!$E$22:$E$24),0) -> 0 | C45: =IFERROR(AVERAGE(PSIRT!$G$22:$G$24),0) -> 0 | D45: =$C45-$B45 -> 0 | E45: =$B45/3 -> 0 | F45: =$C45/3 -> 0 | G45: 0–3
A46: Training & Education | B46: =IFERROR(AVERAGE(PSIRT!$E$26:$E$28),0) -> 0 | C46: =IFERROR(AVERAGE(PSIRT!$G$26:$G$28),0) -> 0 | D46: =$C46-$B46 -> 0 | E46: =$B46/3 -> 0 | F46: =$C46/3 -> 0 | G46: 0–3
A47: ▍ Deception
A48: PREPARE | B48: =IFERROR(AVERAGE(Deception!$E$6:$E$8),0) -> 0 | C48: =IFERROR(AVERAGE(Deception!$G$6:$G$8),0) -> 0 | D48: =$C48-$B48 -> 0 | E48: =$B48/5 -> 0 | F48: =$C48/5 -> 0 | G48: 0–5
A49: EXPOSE | B49: =IFERROR(AVERAGE(Deception!$E$10:$E$11),0) -> 0 | C49: =IFERROR(AVERAGE(Deception!$G$10:$G$11),0) -> 0 | D49: =$C49-$B49 -> 0 | E49: =$B49/5 -> 0 | F49: =$C49/5 -> 0 | G49: 0–5
A50: AFFECT | B50: =IFERROR(AVERAGE(Deception!$E$13:$E$14),0) -> 0 | C50: =IFERROR(AVERAGE(Deception!$G$13:$G$14),0) -> 0 | D50: =$C50-$B50 -> 0 | E50: =$B50/5 -> 0 | F50: =$C50/5 -> 0 | G50: 0–5
A51: ELICIT | B51: =IFERROR(AVERAGE(Deception!$E$16:$E$17),0) -> 0 | C51: =IFERROR(AVERAGE(Deception!$G$16:$G$17),0) -> 0 | D51: =$C51-$B51 -> 0 | E51: =$B51/5 -> 0 | F51: =$C51/5 -> 0 | G51: 0–5
A52: UNDERSTAND | B52: =IFERROR(AVERAGE(Deception!$E$19:$E$21),0) -> 0 | C52: =IFERROR(AVERAGE(Deception!$G$19:$G$21),0) -> 0 | D52: =$C52-$B52 -> 0 | E52: =$B52/5 -> 0 | F52: =$C52/5 -> 0 | G52: 0–5
A53: ▍ Gestão de Vulnerabilidades
A54: PREPARE | B54: =IFERROR(AVERAGE('Vuln Mgmt'!$E$6:$E$8),0) -> 0 | C54: =IFERROR(AVERAGE('Vuln Mgmt'!$G$6:$G$8),0) -> 0 | D54: =$C54-$B54 -> 0 | E54: =$B54/5 -> 0 | F54: =$C54/5 -> 0 | G54: 1–5
A55: IDENTIFY | B55: =IFERROR(AVERAGE('Vuln Mgmt'!$E$10:$E$12),0) -> 0 | C55: =IFERROR(AVERAGE('Vuln Mgmt'!$G$10:$G$12),0) -> 0 | D55: =$C55-$B55 -> 0 | E55: =$B55/5 -> 0 | F55: =$C55/5 -> 0 | G55: 1–5
A56: ANALYZE | B56: =IFERROR(AVERAGE('Vuln Mgmt'!$E$14:$E$16),0) -> 0 | C56: =IFERROR(AVERAGE('Vuln Mgmt'!$G$14:$G$16),0) -> 0 | D56: =$C56-$B56 -> 0 | E56: =$B56/5 -> 0 | F56: =$C56/5 -> 0 | G56: 1–5
A57: COMMUNICATE | B57: =IFERROR(AVERAGE('Vuln Mgmt'!$E$18:$E$20),0) -> 0 | C57: =IFERROR(AVERAGE('Vuln Mgmt'!$G$18:$G$20),0) -> 0 | D57: =$C57-$B57 -> 0 | E57: =$B57/5 -> 0 | F57: =$C57/5 -> 0 | G57: 1–5
A58: TREAT | B58: =IFERROR(AVERAGE('Vuln Mgmt'!$E$22:$E$24),0) -> 0 | C58: =IFERROR(AVERAGE('Vuln Mgmt'!$G$22:$G$24),0) -> 0 | D58: =$C58-$B58 -> 0 | E58: =$B58/5 -> 0 | F58: =$C58/5 -> 0 | G58: 1–5
A59: ▍ Automação & SOAR
A60: Estratégia & casos de uso | B60: =IFERROR(AVERAGE(Automacao!$E$6:$E$8),0) -> 0 | C60: =IFERROR(AVERAGE(Automacao!$G$6:$G$8),0) -> 0 | D60: =$C60-$B60 -> 0 | E60: =$B60/5 -> 0 | F60: =$C60/5 -> 0 | G60: 0–5
A61: Implementação & integrações | B61: =IFERROR(AVERAGE(Automacao!$E$10:$E$12),0) -> 0 | C61: =IFERROR(AVERAGE(Automacao!$G$10:$G$12),0) -> 0 | D61: =$C61-$B61 -> 0 | E61: =$B61/5 -> 0 | F61: =$C61/5 -> 0 | G61: 0–5
A62: Operação & medição | B62: =IFERROR(AVERAGE(Automacao!$E$14:$E$16),0) -> 0 | C62: =IFERROR(AVERAGE(Automacao!$G$14:$G$16),0) -> 0 | D62: =$C62-$B62 -> 0 | E62: =$B62/5 -> 0 | F62: =$C62/5 -> 0 | G62: 0–5
A63: GERAL | E63: =IFERROR(AVERAGE($E$10:$E$62),0) -> 0 | F63: =IFERROR(AVERAGE($F$10:$F$62),0) -> 0
A65: Resumo por domínio (fonte do radar)
A66: Domínio | E66: Maturidade atual | F66: Maturidade meta
A67: CTI | E67: =IFERROR(AVERAGE($E$9:$E$19),0) -> 0 | F67: =IFERROR(AVERAGE($F$9:$F$19),0) -> 0
A68: Threat Hunting | E68: =IFERROR(AVERAGE($E$20:$E$23),0) -> 0 | F68: =IFERROR(AVERAGE($F$20:$F$23),0) -> 0
A69: Detection Engineering | E69: =IFERROR(AVERAGE($E$24:$E$27),0) -> 0 | F69: =IFERROR(AVERAGE($F$24:$F$27),0) -> 0
A70: DFIR / Resposta a Incidentes | E70: =IFERROR(AVERAGE($E$28:$E$30),0) -> 0 | F70: =IFERROR(AVERAGE($F$28:$F$30),0) -> 0
A71: CSIRT | E71: =IFERROR(AVERAGE($E$31:$E$34),0) -> 0 | F71: =IFERROR(AVERAGE($F$31:$F$34),0) -> 0
A72: PSIRT | E72: =IFERROR(AVERAGE($E$35:$E$40),0) -> 0 | F72: =IFERROR(AVERAGE($F$35:$F$40),0) -> 0
A73: Deception | E73: =IFERROR(AVERAGE($E$41:$E$45),0) -> 0 | F73: =IFERROR(AVERAGE($F$41:$F$45),0) -> 0
A74: Gestão de Vulnerabilidades | E74: =IFERROR(AVERAGE($E$46:$E$50),0) -> 0 | F74: =IFERROR(AVERAGE($F$46:$F$50),0) -> 0
A75: Automação & SOAR | E75: =IFERROR(AVERAGE($E$51:$E$53),0) -> 0 | F75: =IFERROR(AVERAGE($F$51:$F$53),0) -> 0
A78: Faixas de classificação (maturidade geral)
A79: 0–9% | B79: Inexistente
A80: 10–29% | B80: Inicial
A81: 30–49% | B81: Em desenvolvimento
A82: 50–69% | B82: Definido
A83: 70–89% | B83: Gerenciado
A84: 90–100% | B84: Otimizado
